{
"slippi_version" : "2.0.1",
"parser_version" : "0.5.0",
"analyzer_version" : "0.5.0",
"game_time" : "2019-04-18T17:56:44",
"stage_id" : 31,
"stage_name" : "BATTLE",
"game_length" : 10920,
"players" : [
 {
 "port" : 1,
 "tag_player" : "",
 "tag_css" : "",
 "tag_code" : "",
 "char_id" : 20,
 "char_name" : "FALCO",
 "player_type" : 0,
 "cpu_level" : 1,
 "color" : 3,
 "team_id" : 0,
 "start_stocks" : 4,
 "end_stocks" : 1,
 "end_pct" : 85,
 "airdodges" : 2,
 "spotdodges" : 3,
 "rolls" : 5,
 "dashdances" : 57,
 "l_cancels_hit" : 35,
 "l_cancels_missed" : 1,
 "techs" : 7,
 "walltechs" : 0,
 "walljumps" : 0,
 "walltechjumps" : 0,
 "missed_techs" : 10,
 "ledge_grabs" : 8,
 "air_frames" : 6020,
 "wavedashes" : 29,
 "wavelands" : 8,
 "neutral_wins" : 9,
 "pokes" : 20,
 "counters" : 4,
 "powershields" : 10,
 "shield_breaks" : 0,
 "grabs" : 1,
 "grab_escapes" : 0,
 "taunts" : 0,
 "meteor_cancels" : 0,
 "damage_dealt" : 435.493,
 "hits_blocked" : 14,
 "shield_stabs" : 1,
 "edge_cancel_aerials" : 1,
 "edge_cancel_specials" : 3,
 "teeter_cancel_aerials" : 0,
 "teeter_cancel_specials" : 0,
 "phantom_hits" : 0,
 "no_impact_lands" : 1,
 "shield_drops" : 7,
 "pivots" : 1,
 "reverse_edgeguards" : 0,
 "self_destructs" : 0,
 "stage_spikes" : 0,
 "short_hops" : 63,
 "full_hops" : 34,
 "shield_time" : 2702,
 "shield_damage" : 188.705,
 "shield_lowest" : 38.8689,
 "total_openings" : 33,
 "mean_kill_openings" : 8.25,
 "mean_kill_percent" : 108.873,
 "mean_opening_percent" : 13.1968,
 "galint_ledgedashes" : 0,
 "mean_galint" : 0,
 "interaction_frames" : {
  "EDGEGUARDING" : 1715,
  "TECHCHASING" : 444,
  "PUNISHING" : 299,
  "SHARKING" : 354,
  "PRESSURING" : 189,
  "OFFENSIVE" : 0,
  "FOOTSIES" : 118,
  "POSITIONING" : 3355,
  "NEUTRAL" : 0,
  "POKING" : 1141,
  "TRADING" : 0,
  "DEFENSIVE" : 0,
  "PRESSURED" : 268,
  "GROUNDING" : 357,
  "PUNISHED" : 544,
  "ESCAPING" : 916,
  "RECOVERING" : 1136
 },
 "interaction_damage" : {
  "EDGEGUARDING" : 103.113,
  "TECHCHASING" : 48.17,
  "PUNISHING" : 42.15,
  "SHARKING" : 0,
  "PRESSURING" : 0,
  "OFFENSIVE" : 0,
  "FOOTSIES" : 0,
  "POSITIONING" : 0,
  "NEUTRAL" : 0,
  "POKING" : 199.06,
  "TRADING" : 0,
  "DEFENSIVE" : 0,
  "PRESSURED" : 7,
  "GROUNDING" : 0,
  "PUNISHED" : 0,
  "ESCAPING" : 12,
  "RECOVERING" : 24
 },
 "moves_landed" : {
  "Forward Smash" : 3,
  "Down Smash" : 1,
  "Neutral Air" : 1,
  "Forward Air" : 1,
  "Back Air" : 11,
  "Down Air" : 13,
  "Neutral Special" : 10,
  "Side Special" : 1,
  "Up Special" : 1,
  "Down Special" : 4,
  "Fast Getup" : 1,
  "Slow Getup" : 1,
  "Up Throw" : 4,
  "_total" : 52
 },
 "attacks" : [
  {
  "move_id" : 14,
  "move_name" : "Fair",
  "cancel_type" : 1,
  "cancel_name" : "LC",
  "punish_id" : 0,
  "hit_id" : 1,
  "game_frame" : 213,
  "anim_frame" : 5,
  "damage" : 9,
  "opening" : "POKING",
  "kill_dir" : "NEUT"
  },
  {
  "move_id" : 21,
  "move_name" : "DownB",
  "cancel_type" : 0,
  "cancel_name" : "",
  "punish_id" : 1,
  "hit_id" : 1,
  "game_frame" : 335,
  "anim_frame" : 10,
  "damage" : 8,
  "opening" : "RECOVERING",
  "kill_dir" : "NEUT"
  },
  {
  "move_id" : 21,
  "move_name" : "DownB",
  "cancel_type" : 0,
  "cancel_name" : "",
  "punish_id" : 2,
  "hit_id" : 1,
  "game_frame" : 648,
  "anim_frame" : 1,
  "damage" : 7.28,
  "opening" : "POKING",
  "kill_dir" : "NEUT"
  },
  {
  "move_id" : 18,
  "move_name" : "NeutB",
  "cancel_type" : 0,
  "cancel_name" : "",
  "punish_id" : 2,
  "hit_id" : 1,
  "game_frame" : 706,
  "anim_frame" : 14,
  "damage" : 3,
  "opening" : "EDGEGUARDING",
  "kill_dir" : "NEUT"
  },
  {
  "move_id" : 18,
  "move_name" : "NeutB",
  "cancel_type" : 0,
  "cancel_name" : "",
  "punish_id" : 2,
  "hit_id" : 1,
  "game_frame" : 719,
  "anim_frame" : 11,
  "damage" : 2.73,
  "opening" : "EDGEGUARDING",
  "kill_dir" : "NEUT"
  },
  {
  "move_id" : 15,
  "move_name" : "Bair",
  "cancel_type" : 2,
  "cancel_name" : "AC",
  "punish_id" : 2,
  "hit_id" : 1,
  "game_frame" : 809,
  "anim_frame" : 17,
  "damage" : 9,
  "opening" : "EDGEGUARDING",
  "kill_dir" : "NEUT"
  },
  {
  "move_id" : 15,
  "move_name" : "Bair",
  "cancel_type" : 2,
  "cancel_name" : "AC",
  "punish_id" : 2,
  "hit_id" : 1,
  "game_frame" : 859,
  "anim_frame" : 10,
  "damage" : 8.19,
  "opening" : "EDGEGUARDING",
  "kill_dir" : "NEUT"
  },
  {
  "move_id" : 17,
  "move_name" : "Dair",
  "cancel_type" : 1,
  "cancel_name" : "LC",
  "punish_id" : 3,
  "hit_id" : 1,
  "game_frame" : 920,
  "anim_frame" : 23,
  "damage" : 9,
  "opening" : "POKING",
  "kill_dir" : "NEUT"
  },
  {
  "move_id" : 21,
  "move_name" : "DownB",
  "cancel_type" : 0,
  "cancel_name" : "",
  "punish_id" : 3,
  "hit_id" : 1,
  "game_frame" : 967,
  "anim_frame" : 3,
  "damage" : 7.44,
  "opening" : "TECHCHASING",
  "kill_dir" : "NEUT"
  },
  {
  "move_id" : 17,
  "move_name" : "Dair",
  "cancel_type" : 1,
  "cancel_name" : "LC",
  "punish_id" : 3,
  "hit_id" : 1,
  "game_frame" : 1018,
  "anim_frame" : 6,
  "damage" : 11.04,
  "opening" : "PUNISHING",
  "kill_dir" : "NEUT"
  },
  {
  "move_id" : 17,
  "move_name" : "Dair",
  "cancel_type" : 1,
  "cancel_name" : "LC",
  "punish_id" : 3,
  "hit_id" : 1,
  "game_frame" : 1063,
  "anim_frame" : 4,
  "damage" : 10.08,
  "opening" : "TECHCHASING",
  "kill_dir" : "NEUT"
  },
  {
  "move_id" : 15,
  "move_name" : "Bair",
  "cancel_type" : 1,
  "cancel_name" : "LC",
  "punish_id" : 3,
  "hit_id" : 1,
  "game_frame" : 1130,
  "anim_frame" : 3,
  "damage" : 13.65,
  "opening" : "TECHCHASING",
  "kill_dir" : "NEUT"
  },
  {
  "move_id" : 10,
  "move_name" : "Fsmash",
  "cancel_type" : 0,
  "cancel_name" : "",
  "punish_id" : 3,
  "hit_id" : 1,
  "game_frame" : 1233,
  "anim_frame" : 16,
  "damage" : 14,
  "opening" : "EDGEGUARDING",
  "kill_dir" : "LEFT"
  },
  {
  "move_id" : 18,
  "move_name" : "NeutB",
  "cancel_type" : 0,
  "cancel_name" : "",
  "punish_id" : 4,
  "hit_id" : 1,
  "game_frame" : 1545,
  "anim_frame" : 7,
  "damage" : 2.97,
  "opening" : "EDGEGUARDING",
  "kill_dir" : "NEUT"
  },
  {
  "move_id" : 15,
  "move_name" : "Bair",
  "cancel_type" : 2,
  "cancel_name" : "AC",
  "punish_id" : 4,
  "hit_id" : 1,
  "game_frame" : 1560,
  "anim_frame" : 4,
  "damage" : 8.1,
  "opening" : "EDGEGUARDING",
  "kill_dir" : "NEUT"
  },
  {
  "move_id" : 17,
  "move_name" : "Dair",
  "cancel_type" : 1,
  "cancel_name" : "LC",
  "punish_id" : 5,
  "hit_id" : 1,
  "game_frame" : 1792,
  "anim_frame" : 4,
  "damage" : 10.68,
  "opening" : "POKING",
  "kill_dir" : "NEUT"
  },
  {
  "move_id" : 55,
  "move_name" : "Uthrow",
  "cancel_type" : 0,
  "cancel_name" : "",
  "punish_id" : 6,
  "hit_id" : 1,
  "game_frame" : 1882,
  "anim_frame" : 6,
  "damage" : 2,
  "opening" : "TECHCHASING",
  "kill_dir" : "NEUT"
  },
  {
  "move_id" : 55,
  "move_name" : "Uthrow",
  "cancel_type" : 0,
  "cancel_name" : "",
  "punish_id" : 6,
  "hit_id" : 2,
  "game_frame" : 1898,
  "anim_frame" : 25,
  "damage" : 1.82,
  "opening" : "PUNISHING",
  "kill_dir" : "NEUT"
  },
  {
  "move_id" : 55,
  "move_name" : "Uthrow",
  "cancel_type" : 0,
  "cancel_name" : "",
  "punish_id" : 6,
  "hit_id" : 3,
  "game_frame" : 1899,
  "anim_frame" : 26,
  "damage" : 1.82,
  "opening" : "PUNISHING",
  "kill_dir" : "NEUT"
  },
  {
  "move_id" : 55,
  "move_name" : "Uthrow",
  "cancel_type" : 0,
  "cancel_name" : "",
  "punish_id" : 6,
  "hit_id" : 4,
  "game_frame" : 1902,
  "anim_frame" : 29,
  "damage" : 1.82,
  "opening" : "PUNISHING",
  "kill_dir" : "NEUT"
  },
  {
  "move_id" : 13,
  "move_name" : "Nair",
  "cancel_type" : 1,
  "cancel_name" : "LC",
  "punish_id" : 6,
  "hit_id" : 1,
  "game_frame" : 1928,
  "anim_frame" : 4,
  "damage" : 12,
  "opening" : "PUNISHING",
  "kill_dir" : "NEUT"
  },
  {
  "move_id" : 15,
  "move_name" : "Bair",
  "cancel_type" : 2,
  "cancel_name" : "AC",
  "punish_id" : 6,
  "hit_id" : 1,
  "game_frame" : 1967,
  "anim_frame" : 3,
  "damage" : 13.65,
  "opening" : "PUNISHING",
  "kill_dir" : "NEUT"
  },
  {
  "move_id" : 15,
  "move_name" : "Bair",
  "cancel_type" : 1,
  "cancel_name" : "LC",
  "punish_id" : 7,
  "hit_id" : 1,
  "game_frame" : 2468,
  "anim_frame" : 3,
  "damage" : 12.6,
  "opening" : "POKING",
  "kill_dir" : "NEUT"
  },
  {
  "move_id" : 18,
  "move_name" : "NeutB",
  "cancel_type" : 0,
  "cancel_name" : "",
  "punish_id" : 8,
  "hit_id" : 1,
  "game_frame" : 3660,
  "anim_frame" : 1,
  "damage" : 3,
  "opening" : "POKING",
  "kill_dir" : "NEUT"
  },
  {
  "move_id" : 17,
  "move_name" : "Dair",
  "cancel_type" : 1,
  "cancel_name" : "LC",
  "punish_id" : 9,
  "hit_id" : 1,
  "game_frame" : 3708,
  "anim_frame" : 10,
  "damage" : 12,
  "opening" : "POKING",
  "kill_dir" : "NEUT"
  },
  {
  "move_id" : 15,
  "move_name" : "Bair",
  "cancel_type" : 2,
  "cancel_name" : "AC",
  "punish_id" : 9,
  "hit_id" : 1,
  "game_frame" : 3802,
  "anim_frame" : 3,
  "damage" : 15,
  "opening" : "TECHCHASING",
  "kill_dir" : "NEUT"
  },
  {
  "move_id" : 18,
  "move_name" : "NeutB",
  "cancel_type" : 0,
  "cancel_name" : "",
  "punish_id" : 9,
  "hit_id" : 1,
  "game_frame" : 3876,
  "anim_frame" : 2,
  "damage" : 2.79,
  "opening" : "EDGEGUARDING",
  "kill_dir" : "NEUT"
  },
  {
  "move_id" : 18,
  "move_name" : "NeutB",
  "cancel_type" : 0,
  "cancel_name" : "",
  "punish_id" : 9,
  "hit_id" : 1,
  "game_frame" : 3903,
  "anim_frame" : 3,
  "damage" : 2.55,
  "opening" : "EDGEGUARDING",
  "kill_dir" : "NEUT"
  },
  {
  "move_id" : 12,
  "move_name" : "Dsmash",
  "cancel_type" : 0,
  "cancel_name" : "",
  "punish_id" : 9,
  "hit_id" : 1,
  "game_frame" : 4047,
  "anim_frame" : 5,
  "damage" : 16.7831,
  "opening" : "EDGEGUARDING",
  "kill_dir" : "DOWN"
  },
  {
  "move_id" : 50,
  "move_name" : "GetupF",
  "cancel_type" : 0,
  "cancel_name" : "",
  "punish_id" : 10,
  "hit_id" : 1,
  "game_frame" : 4898,
  "anim_frame" : 16,
  "damage" : 6,
  "opening" : "ESCAPING",
  "kill_dir" : "NEUT"
  },
  {
  "move_id" : 20,
  "move_name" : "UpB",
  "cancel_type" : 0,
  "cancel_name" : "",
  "punish_id" : 11,
  "hit_id" : 1,
  "game_frame" : 5145,
  "anim_frame" : 15,
  "damage" : 16,
  "opening" : "RECOVERING",
  "kill_dir" : "NEUT"
  },
  {
  "move_id" : 17,
  "move_name" : "Dair",
  "cancel_type" : 1,
  "cancel_name" : "LC",
  "punish_id" : 12,
  "hit_id" : 1,
  "game_frame" : 5786,
  "anim_frame" : 13,
  "damage" : 12,
  "opening" : "POKING",
  "kill_dir" : "NEUT"
  },
  {
  "move_id" : 18,
  "move_name" : "NeutB",
  "cancel_type" : 0,
  "cancel_name" : "",
  "punish_id" : 13,
  "hit_id" : 1,
  "game_frame" : 5867,
  "anim_frame" : 3,
  "damage" : 3,
  "opening" : "POKING",
  "kill_dir" : "NEUT"
  },
  {
  "move_id" : 18,
  "move_name" : "NeutB",
  "cancel_type" : 0,
  "cancel_name" : "",
  "punish_id" : 14,
  "hit_id" : 1,
  "game_frame" : 6001,
  "anim_frame" : 4,
  "damage" : 2.73,
  "opening" : "POKING",
  "kill_dir" : "NEUT"
  },
  {
  "move_id" : 51,
  "move_name" : "GetupS",
  "cancel_type" : 0,
  "cancel_name" : "",
  "punish_id" : 15,
  "hit_id" : 1,
  "game_frame" : 6244,
  "anim_frame" : 18,
  "damage" : 6,
  "opening" : "ESCAPING",
  "kill_dir" : "NEUT"
  },
  {
  "move_id" : 17,
  "move_name" : "Dair",
  "cancel_type" : 1,
  "cancel_name" : "LC",
  "punish_id" : 16,
  "hit_id" : 1,
  "game_frame" : 6340,
  "anim_frame" : 6,
  "damage" : 11.28,
  "opening" : "POKING",
  "kill_dir" : "NEUT"
  },
  {
  "move_id" : 17,
  "move_name" : "Dair",
  "cancel_type" : 0,
  "cancel_name" : "",
  "punish_id" : 17,
  "hit_id" : 1,
  "game_frame" : 6650,
  "anim_frame" : 6,
  "damage" : 10.32,
  "opening" : "POKING",
  "kill_dir" : "DOWN"
  },
  {
  "move_id" : 15,
  "move_name" : "Bair",
  "cancel_type" : 2,
  "cancel_name" : "AC",
  "punish_id" : 18,
  "hit_id" : 1,
  "game_frame" : 7217,
  "anim_frame" : 3,
  "damage" : 15,
  "opening" : "POKING",
  "kill_dir" : "NEUT"
  },
  {
  "move_id" : 21,
  "move_name" : "DownB",
  "cancel_type" : 0,
  "cancel_name" : "",
  "punish_id" : 18,
  "hit_id" : 1,
  "game_frame" : 7249,
  "anim_frame" : 0,
  "damage" : 8,
  "opening" : "EDGEGUARDING",
  "kill_dir" : "NEUT"
  },
  {
  "move_id" : 15,
  "move_name" : "Bair",
  "cancel_type" : 1,
  "cancel_name" : "LC",
  "punish_id" : 19,
  "hit_id" : 1,
  "game_frame" : 7521,
  "anim_frame" : 17,
  "damage" : 8.28,
  "opening" : "POKING",
  "kill_dir" : "NEUT"
  },
  {
  "move_id" : 18,
  "move_name" : "NeutB",
  "cancel_type" : 0,
  "cancel_name" : "",
  "punish_id" : 20,
  "hit_id" : 1,
  "game_frame" : 8101,
  "anim_frame" : 4,
  "damage" : 3,
  "opening" : "POKING",
  "kill_dir" : "NEUT"
  },
  {
  "move_id" : 17,
  "move_name" : "Dair",
  "cancel_type" : 1,
  "cancel_name" : "LC",
  "punish_id" : 21,
  "hit_id" : 1,
  "game_frame" : 8153,
  "anim_frame" : 4,
  "damage" : 12,
  "opening" : "POKING",
  "kill_dir" : "NEUT"
  },
  {
  "move_id" : 17,
  "move_name" : "Dair",
  "cancel_type" : 1,
  "cancel_name" : "LC",
  "punish_id" : 22,
  "hit_id" : 1,
  "game_frame" : 8716,
  "anim_frame" : 20,
  "damage" : 8.19,
  "opening" : "POKING",
  "kill_dir" : "NEUT"
  },
  {
  "move_id" : 17,
  "move_name" : "Dair",
  "cancel_type" : 0,
  "cancel_name" : "",
  "punish_id" : 23,
  "hit_id" : 1,
  "game_frame" : 9305,
  "anim_frame" : 6,
  "damage" : 9.96,
  "opening" : "POKING",
  "kill_dir" : "NEUT"
  },
  {
  "move_id" : 18,
  "move_name" : "NeutB",
  "cancel_type" : 0,
  "cancel_name" : "",
  "punish_id" : 24,
  "hit_id" : 1,
  "game_frame" : 9610,
  "anim_frame" : 1,
  "damage" : 2.82,
  "opening" : "POKING",
  "kill_dir" : "NEUT"
  },
  {
  "move_id" : 15,
  "move_name" : "Bair",
  "cancel_type" : 0,
  "cancel_name" : "",
  "punish_id" : 25,
  "hit_id" : 1,
  "game_frame" : 9813,
  "anim_frame" : 13,
  "damage" : 9,
  "opening" : "POKING",
  "kill_dir" : "NEUT"
  },
  {
  "move_id" : 19,
  "move_name" : "SideB",
  "cancel_type" : 0,
  "cancel_name" : "",
  "punish_id" : 26,
  "hit_id" : 1,
  "game_frame" : 10030,
  "anim_frame" : 3,
  "damage" : 7,
  "opening" : "PRESSURED",
  "kill_dir" : "NEUT"
  },
  {
  "move_id" : 15,
  "move_name" : "Bair",
  "cancel_type" : 2,
  "cancel_name" : "AC",
  "punish_id" : 26,
  "hit_id" : 1,
  "game_frame" : 10077,
  "anim_frame" : 3,
  "damage" : 13.8,
  "opening" : "EDGEGUARDING",
  "kill_dir" : "NEUT"
  },
  {
  "move_id" : 10,
  "move_name" : "Fsmash",
  "cancel_type" : 0,
  "cancel_name" : "",
  "punish_id" : 27,
  "hit_id" : 1,
  "game_frame" : 10495,
  "anim_frame" : 11,
  "damage" : 17,
  "opening" : "POKING",
  "kill_dir" : "NEUT"
  },
  {
  "move_id" : 255,
  "move_name" : "(o)",
  "cancel_type" : 0,
  "cancel_name" : "",
  "punish_id" : 27,
  "hit_id" : 1,
  "game_frame" : 10613,
  "anim_frame" : 1,
  "damage" : 1,
  "opening" : "EDGEGUARDING",
  "kill_dir" : "NEUT"
  },
  {
  "move_id" : 17,
  "move_name" : "Dair",
  "cancel_type" : 1,
  "cancel_name" : "LC",
  "punish_id" : 28,
  "hit_id" : 1,
  "game_frame" : 10816,
  "anim_frame" : 4,
  "damage" : 10.92,
  "opening" : "POKING",
  "kill_dir" : "NEUT"
  },
  {
  "move_id" : 17,
  "move_name" : "Dair",
  "cancel_type" : 2,
  "cancel_name" : "AC",
  "punish_id" : 28,
  "hit_id" : 1,
  "game_frame" : 10861,
  "anim_frame" : 5,
  "damage" : 10.2,
  "opening" : "EDGEGUARDING",
  "kill_dir" : "DOWN"
  }
 ],
 "punishes" : [
  {
  "start_frame" : 213,
  "end_frame" : 270,
  "start_pct" : 0,
  "end_pct" : 9,
  "num_moves" : 1,
  "last_move_id" : 14,
  "last_move_name" : "Fair",
  "opening" : "UNUSED",
  "kill_dir" : "NEUT"
  },
  {
  "start_frame" : 335,
  "end_frame" : 447,
  "start_pct" : 9,
  "end_pct" : 17,
  "num_moves" : 1,
  "last_move_id" : 21,
  "last_move_name" : "DownB",
  "opening" : "UNUSED",
  "kill_dir" : "NEUT"
  },
  {
  "start_frame" : 648,
  "end_frame" : 919,
  "start_pct" : 17,
  "end_pct" : 47.2,
  "num_moves" : 5,
  "last_move_id" : 15,
  "last_move_name" : "Bair",
  "opening" : "UNUSED",
  "kill_dir" : "NEUT"
  },
  {
  "start_frame" : 920,
  "end_frame" : 1325,
  "start_pct" : 47.2,
  "end_pct" : 112.41,
  "num_moves" : 6,
  "last_move_id" : 10,
  "last_move_name" : "Fsmash",
  "opening" : "UNUSED",
  "kill_dir" : "LEFT"
  },
  {
  "start_frame" : 1545,
  "end_frame" : 1618,
  "start_pct" : 0,
  "end_pct" : 11.07,
  "num_moves" : 2,
  "last_move_id" : 15,
  "last_move_name" : "Bair",
  "opening" : "UNUSED",
  "kill_dir" : "NEUT"
  },
  {
  "start_frame" : 1792,
  "end_frame" : 1827,
  "start_pct" : 11.07,
  "end_pct" : 21.75,
  "num_moves" : 1,
  "last_move_id" : 17,
  "last_move_name" : "Dair",
  "opening" : "UNUSED",
  "kill_dir" : "NEUT"
  },
  {
  "start_frame" : 1882,
  "end_frame" : 2047,
  "start_pct" : 21.75,
  "end_pct" : 54.86,
  "num_moves" : 6,
  "last_move_id" : 15,
  "last_move_name" : "Bair",
  "opening" : "UNUSED",
  "kill_dir" : "NEUT"
  },
  {
  "start_frame" : 2468,
  "end_frame" : 2582,
  "start_pct" : 54.86,
  "end_pct" : 67.46,
  "num_moves" : 1,
  "last_move_id" : 15,
  "last_move_name" : "Bair",
  "opening" : "UNUSED",
  "kill_dir" : "NEUT"
  },
  {
  "start_frame" : 3660,
  "end_frame" : 3700,
  "start_pct" : 67.46,
  "end_pct" : 70.46,
  "num_moves" : 1,
  "last_move_id" : 18,
  "last_move_name" : "NeutB",
  "opening" : "UNUSED",
  "kill_dir" : "NEUT"
  },
  {
  "start_frame" : 3708,
  "end_frame" : 4234,
  "start_pct" : 70.46,
  "end_pct" : 119.583,
  "num_moves" : 5,
  "last_move_id" : 12,
  "last_move_name" : "Dsmash",
  "opening" : "UNUSED",
  "kill_dir" : "DOWN"
  },
  {
  "start_frame" : 4898,
  "end_frame" : 4929,
  "start_pct" : 0,
  "end_pct" : 6,
  "num_moves" : 1,
  "last_move_id" : 50,
  "last_move_name" : "GetupF",
  "opening" : "UNUSED",
  "kill_dir" : "NEUT"
  },
  {
  "start_frame" : 5145,
  "end_frame" : 5255,
  "start_pct" : 6,
  "end_pct" : 22,
  "num_moves" : 1,
  "last_move_id" : 20,
  "last_move_name" : "UpB",
  "opening" : "UNUSED",
  "kill_dir" : "NEUT"
  },
  {
  "start_frame" : 5786,
  "end_frame" : 5845,
  "start_pct" : 22,
  "end_pct" : 34,
  "num_moves" : 1,
  "last_move_id" : 17,
  "last_move_name" : "Dair",
  "opening" : "UNUSED",
  "kill_dir" : "NEUT"
  },
  {
  "start_frame" : 5867,
  "end_frame" : 5907,
  "start_pct" : 34,
  "end_pct" : 37,
  "num_moves" : 1,
  "last_move_id" : 18,
  "last_move_name" : "NeutB",
  "opening" : "UNUSED",
  "kill_dir" : "NEUT"
  },
  {
  "start_frame" : 6001,
  "end_frame" : 6040,
  "start_pct" : 37,
  "end_pct" : 39.73,
  "num_moves" : 1,
  "last_move_id" : 18,
  "last_move_name" : "NeutB",
  "opening" : "UNUSED",
  "kill_dir" : "NEUT"
  },
  {
  "start_frame" : 6244,
  "end_frame" : 6326,
  "start_pct" : 39.73,
  "end_pct" : 45.73,
  "num_moves" : 1,
  "last_move_id" : 51,
  "last_move_name" : "GetupS",
  "opening" : "UNUSED",
  "kill_dir" : "NEUT"
  },
  {
  "start_frame" : 6340,
  "end_frame" : 6419,
  "start_pct" : 45.73,
  "end_pct" : 57.01,
  "num_moves" : 1,
  "last_move_id" : 17,
  "last_move_name" : "Dair",
  "opening" : "UNUSED",
  "kill_dir" : "NEUT"
  },
  {
  "start_frame" : 6650,
  "end_frame" : 6792,
  "start_pct" : 57.01,
  "end_pct" : 67.33,
  "num_moves" : 1,
  "last_move_id" : 17,
  "last_move_name" : "Dair",
  "opening" : "UNUSED",
  "kill_dir" : "DOWN"
  },
  {
  "start_frame" : 7217,
  "end_frame" : 7380,
  "start_pct" : 0,
  "end_pct" : 23,
  "num_moves" : 2,
  "last_move_id" : 21,
  "last_move_name" : "DownB",
  "opening" : "UNUSED",
  "kill_dir" : "NEUT"
  },
  {
  "start_frame" : 7521,
  "end_frame" : 7570,
  "start_pct" : 23,
  "end_pct" : 31.28,
  "num_moves" : 1,
  "last_move_id" : 15,
  "last_move_name" : "Bair",
  "opening" : "UNUSED",
  "kill_dir" : "NEUT"
  },
  {
  "start_frame" : 8101,
  "end_frame" : 8141,
  "start_pct" : 31.28,
  "end_pct" : 34.28,
  "num_moves" : 1,
  "last_move_id" : 18,
  "last_move_name" : "NeutB",
  "opening" : "UNUSED",
  "kill_dir" : "NEUT"
  },
  {
  "start_frame" : 8153,
  "end_frame" : 8217,
  "start_pct" : 34.28,
  "end_pct" : 46.28,
  "num_moves" : 1,
  "last_move_id" : 17,
  "last_move_name" : "Dair",
  "opening" : "UNUSED",
  "kill_dir" : "NEUT"
  },
  {
  "start_frame" : 8716,
  "end_frame" : 8788,
  "start_pct" : 46.28,
  "end_pct" : 54.47,
  "num_moves" : 1,
  "last_move_id" : 17,
  "last_move_name" : "Dair",
  "opening" : "UNUSED",
  "kill_dir" : "NEUT"
  },
  {
  "start_frame" : 9305,
  "end_frame" : 9354,
  "start_pct" : 54.47,
  "end_pct" : 64.43,
  "num_moves" : 1,
  "last_move_id" : 17,
  "last_move_name" : "Dair",
  "opening" : "UNUSED",
  "kill_dir" : "NEUT"
  },
  {
  "start_frame" : 9610,
  "end_frame" : 9672,
  "start_pct" : 64.43,
  "end_pct" : 67.25,
  "num_moves" : 1,
  "last_move_id" : 18,
  "last_move_name" : "NeutB",
  "opening" : "UNUSED",
  "kill_dir" : "NEUT"
  },
  {
  "start_frame" : 9813,
  "end_frame" : 9867,
  "start_pct" : 67.25,
  "end_pct" : 76.25,
  "num_moves" : 1,
  "last_move_id" : 15,
  "last_move_name" : "Bair",
  "opening" : "UNUSED",
  "kill_dir" : "NEUT"
  },
  {
  "start_frame" : 10030,
  "end_frame" : 10206,
  "start_pct" : 76.25,
  "end_pct" : 97.05,
  "num_moves" : 2,
  "last_move_id" : 15,
  "last_move_name" : "Bair",
  "opening" : "UNUSED",
  "kill_dir" : "NEUT"
  },
  {
  "start_frame" : 10495,
  "end_frame" : 10785,
  "start_pct" : 97.05,
  "end_pct" : 115.05,
  "num_moves" : 2,
  "last_move_id" : 10,
  "last_move_name" : "Fsmash",
  "opening" : "UNUSED",
  "kill_dir" : "NEUT"
  },
  {
  "start_frame" : 10816,
  "end_frame" : 10919,
  "start_pct" : 115.05,
  "end_pct" : 136.17,
  "num_moves" : 2,
  "last_move_id" : 17,
  "last_move_name" : "Dair",
  "opening" : "UNUSED",
  "kill_dir" : "DOWN"
  }
 ]
 },
 {
 "port" : 3,
 "tag_player" : "",
 "tag_css" : "",
 "tag_code" : "",
 "char_id" : 9,
 "char_name" : "MARTH",
 "player_type" : 0,
 "cpu_level" : 1,
 "color" : 1,
 "team_id" : 0,
 "start_stocks" : 4,
 "end_stocks" : 0,
 "end_pct" : 136,
 "airdodges" : 0,
 "spotdodges" : 0,
 "rolls" : 8,
 "dashdances" : 57,
 "l_cancels_hit" : 41,
 "l_cancels_missed" : 5,
 "techs" : 5,
 "walltechs" : 0,
 "walljumps" : 0,
 "walltechjumps" : 1,
 "missed_techs" : 6,
 "ledge_grabs" : 2,
 "air_frames" : 5798,
 "wavedashes" : 18,
 "wavelands" : 2,
 "neutral_wins" : 8,
 "pokes" : 16,
 "counters" : 3,
 "powershields" : 0,
 "shield_breaks" : 0,
 "grabs" : 4,
 "grab_escapes" : 0,
 "taunts" : 0,
 "meteor_cancels" : 0,
 "damage_dealt" : 394.54,
 "hits_blocked" : 9,
 "shield_stabs" : 2,
 "edge_cancel_aerials" : 1,
 "edge_cancel_specials" : 0,
 "teeter_cancel_aerials" : 0,
 "teeter_cancel_specials" : 0,
 "phantom_hits" : 0,
 "no_impact_lands" : 0,
 "shield_drops" : 7,
 "pivots" : 6,
 "reverse_edgeguards" : 0,
 "self_destructs" : 0,
 "stage_spikes" : 0,
 "short_hops" : 10,
 "full_hops" : 67,
 "shield_time" : 2086,
 "shield_damage" : 145.434,
 "shield_lowest" : 46.0151,
 "total_openings" : 27,
 "mean_kill_openings" : 9,
 "mean_kill_percent" : 131.513,
 "mean_opening_percent" : 14.6126,
 "galint_ledgedashes" : 0,
 "mean_galint" : 0,
 "interaction_frames" : {
  "EDGEGUARDING" : 1136,
  "TECHCHASING" : 916,
  "PUNISHING" : 544,
  "SHARKING" : 357,
  "PRESSURING" : 268,
  "OFFENSIVE" : 0,
  "FOOTSIES" : 118,
  "POSITIONING" : 3355,
  "NEUTRAL" : 0,
  "POKING" : 1141,
  "TRADING" : 0,
  "DEFENSIVE" : 0,
  "PRESSURED" : 189,
  "GROUNDING" : 354,
  "PUNISHED" : 299,
  "ESCAPING" : 444,
  "RECOVERING" : 1715
 },
 "interaction_damage" : {
  "EDGEGUARDING" : 63.27,
  "TECHCHASING" : 62.81,
  "PUNISHING" : 101.58,
  "SHARKING" : 0,
  "PRESSURING" : 0,
  "OFFENSIVE" : 0,
  "FOOTSIES" : 0,
  "POSITIONING" : 0,
  "NEUTRAL" : 0,
  "POKING" : 166.88,
  "TRADING" : 0,
  "DEFENSIVE" : 0,
  "PRESSURED" : 0,
  "GROUNDING" : 0,
  "PUNISHED" : 0,
  "ESCAPING" : 0,
  "RECOVERING" : 0
 },
 "moves_landed" : {
  "Jab 2" : 1,
  "Up Tilt" : 5,
  "Down Tilt" : 3,
  "Neutral Air" : 18,
  "Forward Air" : 6,
  "Up Air" : 7,
  "Down Air" : 2,
  "Neutral Special" : 1,
  "Up Special" : 2,
  "Forward Throw" : 1,
  "Up Throw" : 3,
  "_total" : 49
 },
 "attacks" : [
  {
  "move_id" : 13,
  "move_name" : "Nair",
  "cancel_type" : 2,
  "cancel_name" : "AC",
  "punish_id" : 0,
  "hit_id" : 1,
  "game_frame" : 305,
  "anim_frame" : 5,
  "damage" : 4,
  "opening" : "EDGEGUARDING",
  "kill_dir" : "NEUT"
  },
  {
  "move_id" : 13,
  "move_name" : "Nair",
  "cancel_type" : 2,
  "cancel_name" : "AC",
  "punish_id" : 1,
  "hit_id" : 1,
  "game_frame" : 568,
  "anim_frame" : 5,
  "damage" : 3.64,
  "opening" : "POKING",
  "kill_dir" : "NEUT"
  },
  {
  "move_id" : 13,
  "move_name" : "Nair",
  "cancel_type" : 2,
  "cancel_name" : "AC",
  "punish_id" : 1,
  "hit_id" : 2,
  "game_frame" : 584,
  "anim_frame" : 18,
  "damage" : 8.3,
  "opening" : "PUNISHING",
  "kill_dir" : "NEUT"
  },
  {
  "move_id" : 13,
  "move_name" : "Nair",
  "cancel_type" : 2,
  "cancel_name" : "AC",
  "punish_id" : 2,
  "hit_id" : 1,
  "game_frame" : 2219,
  "anim_frame" : 20,
  "damage" : 10,
  "opening" : "POKING",
  "kill_dir" : "NEUT"
  },
  {
  "move_id" : 9,
  "move_name" : "Dtilt",
  "cancel_type" : 0,
  "cancel_name" : "",
  "punish_id" : 3,
  "hit_id" : 1,
  "game_frame" : 2305,
  "anim_frame" : 6,
  "damage" : 10,
  "opening" : "POKING",
  "kill_dir" : "NEUT"
  },
  {
  "move_id" : 13,
  "move_name" : "Nair",
  "cancel_type" : 2,
  "cancel_name" : "AC",
  "punish_id" : 4,
  "hit_id" : 1,
  "game_frame" : 2818,
  "anim_frame" : 15,
  "damage" : 9.2,
  "opening" : "POKING",
  "kill_dir" : "NEUT"
  },
  {
  "move_id" : 55,
  "move_name" : "Uthrow",
  "cancel_type" : 0,
  "cancel_name" : "",
  "punish_id" : 4,
  "hit_id" : 1,
  "game_frame" : 2937,
  "anim_frame" : 11,
  "damage" : 4,
  "opening" : "TECHCHASING",
  "kill_dir" : "NEUT"
  },
  {
  "move_id" : 8,
  "move_name" : "Utilt",
  "cancel_type" : 0,
  "cancel_name" : "",
  "punish_id" : 4,
  "hit_id" : 1,
  "game_frame" : 2977,
  "anim_frame" : 5,
  "damage" : 9,
  "opening" : "PUNISHING",
  "kill_dir" : "NEUT"
  },
  {
  "move_id" : 16,
  "move_name" : "Uair",
  "cancel_type" : 1,
  "cancel_name" : "LC",
  "punish_id" : 4,
  "hit_id" : 1,
  "game_frame" : 3058,
  "anim_frame" : 7,
  "damage" : 13,
  "opening" : "TECHCHASING",
  "kill_dir" : "NEUT"
  },
  {
  "move_id" : 16,
  "move_name" : "Uair",
  "cancel_type" : 1,
  "cancel_name" : "LC",
  "punish_id" : 4,
  "hit_id" : 1,
  "game_frame" : 3133,
  "anim_frame" : 5,
  "damage" : 11.83,
  "opening" : "TECHCHASING",
  "kill_dir" : "NEUT"
  },
  {
  "move_id" : 16,
  "move_name" : "Uair",
  "cancel_type" : 1,
  "cancel_name" : "LC",
  "punish_id" : 4,
  "hit_id" : 1,
  "game_frame" : 3184,
  "anim_frame" : 4,
  "damage" : 8.3,
  "opening" : "PUNISHING",
  "kill_dir" : "NEUT"
  },
  {
  "move_id" : 17,
  "move_name" : "Dair",
  "cancel_type" : 0,
  "cancel_name" : "",
  "punish_id" : 4,
  "hit_id" : 1,
  "game_frame" : 3221,
  "anim_frame" : 5,
  "damage" : 9,
  "opening" : "PUNISHING",
  "kill_dir" : "NEUT"
  },
  {
  "move_id" : 16,
  "move_name" : "Uair",
  "cancel_type" : 1,
  "cancel_name" : "LC",
  "punish_id" : 4,
  "hit_id" : 1,
  "game_frame" : 3296,
  "anim_frame" : 6,
  "damage" : 7.9,
  "opening" : "EDGEGUARDING",
  "kill_dir" : "NEUT"
  },
  {
  "move_id" : 14,
  "move_name" : "Fair",
  "cancel_type" : 0,
  "cancel_name" : "",
  "punish_id" : 4,
  "hit_id" : 1,
  "game_frame" : 3344,
  "anim_frame" : 4,
  "damage" : 9,
  "opening" : "EDGEGUARDING",
  "kill_dir" : "NEUT"
  },
  {
  "move_id" : 17,
  "move_name" : "Dair",
  "cancel_type" : 1,
  "cancel_name" : "LC",
  "punish_id" : 4,
  "hit_id" : 1,
  "game_frame" : 3384,
  "anim_frame" : 5,
  "damage" : 8.37,
  "opening" : "EDGEGUARDING",
  "kill_dir" : "DOWN"
  },
  {
  "move_id" : 8,
  "move_name" : "Utilt",
  "cancel_type" : 0,
  "cancel_name" : "",
  "punish_id" : 5,
  "hit_id" : 1,
  "game_frame" : 4526,
  "anim_frame" : 7,
  "damage" : 12,
  "opening" : "POKING",
  "kill_dir" : "NEUT"
  },
  {
  "move_id" : 13,
  "move_name" : "Nair",
  "cancel_type" : 2,
  "cancel_name" : "AC",
  "punish_id" : 6,
  "hit_id" : 1,
  "game_frame" : 4729,
  "anim_frame" : 20,
  "damage" : 10,
  "opening" : "POKING",
  "kill_dir" : "NEUT"
  },
  {
  "move_id" : 13,
  "move_name" : "Nair",
  "cancel_type" : 1,
  "cancel_name" : "LC",
  "punish_id" : 7,
  "hit_id" : 1,
  "game_frame" : 4820,
  "anim_frame" : 5,
  "damage" : 3.64,
  "opening" : "POKING",
  "kill_dir" : "NEUT"
  },
  {
  "move_id" : 13,
  "move_name" : "Nair",
  "cancel_type" : 1,
  "cancel_name" : "LC",
  "punish_id" : 7,
  "hit_id" : 2,
  "game_frame" : 4832,
  "anim_frame" : 14,
  "damage" : 8.3,
  "opening" : "PUNISHING",
  "kill_dir" : "NEUT"
  },
  {
  "move_id" : 53,
  "move_name" : "Fthrow",
  "cancel_type" : 0,
  "cancel_name" : "",
  "punish_id" : 7,
  "hit_id" : 1,
  "game_frame" : 4946,
  "anim_frame" : 13,
  "damage" : 4,
  "opening" : "TECHCHASING",
  "kill_dir" : "NEUT"
  },
  {
  "move_id" : 9,
  "move_name" : "Dtilt",
  "cancel_type" : 0,
  "cancel_name" : "",
  "punish_id" : 7,
  "hit_id" : 1,
  "game_frame" : 4966,
  "anim_frame" : 6,
  "damage" : 9,
  "opening" : "EDGEGUARDING",
  "kill_dir" : "NEUT"
  },
  {
  "move_id" : 3,
  "move_name" : "Jab2",
  "cancel_type" : 0,
  "cancel_name" : "",
  "punish_id" : 7,
  "hit_id" : 1,
  "game_frame" : 5051,
  "anim_frame" : 3,
  "damage" : 4,
  "opening" : "EDGEGUARDING",
  "kill_dir" : "NEUT"
  },
  {
  "move_id" : 8,
  "move_name" : "Utilt",
  "cancel_type" : 0,
  "cancel_name" : "",
  "punish_id" : 8,
  "hit_id" : 1,
  "game_frame" : 5287,
  "anim_frame" : 7,
  "damage" : 11.52,
  "opening" : "POKING",
  "kill_dir" : "NEUT"
  },
  {
  "move_id" : 14,
  "move_name" : "Fair",
  "cancel_type" : 0,
  "cancel_name" : "",
  "punish_id" : 8,
  "hit_id" : 1,
  "game_frame" : 5335,
  "anim_frame" : 3,
  "damage" : 10,
  "opening" : "PUNISHING",
  "kill_dir" : "NEUT"
  },
  {
  "move_id" : 20,
  "move_name" : "UpB",
  "cancel_type" : 0,
  "cancel_name" : "",
  "punish_id" : 8,
  "hit_id" : 1,
  "game_frame" : 5376,
  "anim_frame" : 4,
  "damage" : 13,
  "opening" : "EDGEGUARDING",
  "kill_dir" : "NEUT"
  },
  {
  "move_id" : 255,
  "move_name" : "(o)",
  "cancel_type" : 0,
  "cancel_name" : "",
  "punish_id" : 8,
  "hit_id" : 1,
  "game_frame" : 5473,
  "anim_frame" : 14,
  "damage" : 1,
  "opening" : "EDGEGUARDING",
  "kill_dir" : "RIGHT"
  },
  {
  "move_id" : 13,
  "move_name" : "Nair",
  "cancel_type" : 2,
  "cancel_name" : "AC",
  "punish_id" : 9,
  "hit_id" : 1,
  "game_frame" : 6103,
  "anim_frame" : 14,
  "damage" : 9.5,
  "opening" : "POKING",
  "kill_dir" : "NEUT"
  },
  {
  "move_id" : 13,
  "move_name" : "Nair",
  "cancel_type" : 2,
  "cancel_name" : "AC",
  "punish_id" : 10,
  "hit_id" : 1,
  "game_frame" : 6164,
  "anim_frame" : 6,
  "damage" : 3.52,
  "opening" : "POKING",
  "kill_dir" : "NEUT"
  },
  {
  "move_id" : 13,
  "move_name" : "Nair",
  "cancel_type" : 2,
  "cancel_name" : "AC",
  "punish_id" : 10,
  "hit_id" : 2,
  "game_frame" : 6175,
  "anim_frame" : 14,
  "damage" : 8.2,
  "opening" : "PUNISHING",
  "kill_dir" : "NEUT"
  },
  {
  "move_id" : 9,
  "move_name" : "Dtilt",
  "cancel_type" : 0,
  "cancel_name" : "",
  "punish_id" : 11,
  "hit_id" : 1,
  "game_frame" : 6471,
  "anim_frame" : 6,
  "damage" : 7.76,
  "opening" : "POKING",
  "kill_dir" : "NEUT"
  },
  {
  "move_id" : 14,
  "move_name" : "Fair",
  "cancel_type" : 2,
  "cancel_name" : "AC",
  "punish_id" : 11,
  "hit_id" : 1,
  "game_frame" : 6511,
  "anim_frame" : 4,
  "damage" : 9.5,
  "opening" : "PUNISHING",
  "kill_dir" : "NEUT"
  },
  {
  "move_id" : 13,
  "move_name" : "Nair",
  "cancel_type" : 0,
  "cancel_name" : "",
  "punish_id" : 12,
  "hit_id" : 1,
  "game_frame" : 6650,
  "anim_frame" : 5,
  "damage" : 3.48,
  "opening" : "POKING",
  "kill_dir" : "NEUT"
  },
  {
  "move_id" : 16,
  "move_name" : "Uair",
  "cancel_type" : 0,
  "cancel_name" : "",
  "punish_id" : 13,
  "hit_id" : 1,
  "game_frame" : 7042,
  "anim_frame" : 7,
  "damage" : 13,
  "opening" : "POKING",
  "kill_dir" : "NEUT"
  },
  {
  "move_id" : 16,
  "move_name" : "Uair",
  "cancel_type" : 1,
  "cancel_name" : "LC",
  "punish_id" : 13,
  "hit_id" : 1,
  "game_frame" : 7123,
  "anim_frame" : 6,
  "damage" : 9.1,
  "opening" : "TECHCHASING",
  "kill_dir" : "NEUT"
  },
  {
  "move_id" : 14,
  "move_name" : "Fair",
  "cancel_type" : 1,
  "cancel_name" : "LC",
  "punish_id" : 14,
  "hit_id" : 1,
  "game_frame" : 7344,
  "anim_frame" : 4,
  "damage" : 10,
  "opening" : "POKING",
  "kill_dir" : "NEUT"
  },
  {
  "move_id" : 55,
  "move_name" : "Uthrow",
  "cancel_type" : 0,
  "cancel_name" : "",
  "punish_id" : 15,
  "hit_id" : 1,
  "game_frame" : 7631,
  "anim_frame" : 11,
  "damage" : 4,
  "opening" : "TECHCHASING",
  "kill_dir" : "NEUT"
  },
  {
  "move_id" : 8,
  "move_name" : "Utilt",
  "cancel_type" : 0,
  "cancel_name" : "",
  "punish_id" : 16,
  "hit_id" : 1,
  "game_frame" : 7726,
  "anim_frame" : 7,
  "damage" : 12,
  "opening" : "POKING",
  "kill_dir" : "NEUT"
  },
  {
  "move_id" : 18,
  "move_name" : "NeutB",
  "cancel_type" : 0,
  "cancel_name" : "",
  "punish_id" : 16,
  "hit_id" : 1,
  "game_frame" : 7800,
  "anim_frame" : 5,
  "damage" : 7,
  "opening" : "EDGEGUARDING",
  "kill_dir" : "DOWN"
  },
  {
  "move_id" : 14,
  "move_name" : "Fair",
  "cancel_type" : 1,
  "cancel_name" : "LC",
  "punish_id" : 17,
  "hit_id" : 1,
  "game_frame" : 8197,
  "anim_frame" : 4,
  "damage" : 12.22,
  "opening" : "PUNISHING",
  "kill_dir" : "NEUT"
  },
  {
  "move_id" : 8,
  "move_name" : "Utilt",
  "cancel_type" : 0,
  "cancel_name" : "",
  "punish_id" : 17,
  "hit_id" : 1,
  "game_frame" : 8227,
  "anim_frame" : 5,
  "damage" : 11.16,
  "opening" : "PUNISHING",
  "kill_dir" : "NEUT"
  },
  {
  "move_id" : 13,
  "move_name" : "Nair",
  "cancel_type" : 2,
  "cancel_name" : "AC",
  "punish_id" : 18,
  "hit_id" : 1,
  "game_frame" : 8808,
  "anim_frame" : 14,
  "damage" : 10,
  "opening" : "POKING",
  "kill_dir" : "NEUT"
  },
  {
  "move_id" : 13,
  "move_name" : "Nair",
  "cancel_type" : 0,
  "cancel_name" : "",
  "punish_id" : 19,
  "hit_id" : 1,
  "game_frame" : 9305,
  "anim_frame" : 14,
  "damage" : 9.1,
  "opening" : "POKING",
  "kill_dir" : "NEUT"
  },
  {
  "move_id" : 55,
  "move_name" : "Uthrow",
  "cancel_type" : 0,
  "cancel_name" : "",
  "punish_id" : 19,
  "hit_id" : 1,
  "game_frame" : 9439,
  "anim_frame" : 11,
  "damage" : 3.88,
  "opening" : "TECHCHASING",
  "kill_dir" : "NEUT"
  },
  {
  "move_id" : 16,
  "move_name" : "Uair",
  "cancel_type" : 1,
  "cancel_name" : "LC",
  "punish_id" : 19,
  "hit_id" : 1,
  "game_frame" : 9503,
  "anim_frame" : 5,
  "damage" : 13,
  "opening" : "TECHCHASING",
  "kill_dir" : "NEUT"
  },
  {
  "move_id" : 14,
  "move_name" : "Fair",
  "cancel_type" : 1,
  "cancel_name" : "LC",
  "punish_id" : 20,
  "hit_id" : 1,
  "game_frame" : 9705,
  "anim_frame" : 3,
  "damage" : 8.64,
  "opening" : "POKING",
  "kill_dir" : "NEUT"
  },
  {
  "move_id" : 13,
  "move_name" : "Nair",
  "cancel_type" : 1,
  "cancel_name" : "LC",
  "punish_id" : 21,
  "hit_id" : 1,
  "game_frame" : 9813,
  "anim_frame" : 5,
  "damage" : 3.56,
  "opening" : "POKING",
  "kill_dir" : "NEUT"
  },
  {
  "move_id" : 13,
  "move_name" : "Nair",
  "cancel_type" : 2,
  "cancel_name" : "AC",
  "punish_id" : 22,
  "hit_id" : 1,
  "game_frame" : 9896,
  "anim_frame" : 5,
  "damage" : 3.28,
  "opening" : "POKING",
  "kill_dir" : "NEUT"
  },
  {
  "move_id" : 13,
  "move_name" : "Nair",
  "cancel_type" : 2,
  "cancel_name" : "AC",
  "punish_id" : 22,
  "hit_id" : 2,
  "game_frame" : 9913,
  "anim_frame" : 19,
  "damage" : 7.6,
  "opening" : "PUNISHING",
  "kill_dir" : "NEUT"
  },
  {
  "move_id" : 13,
  "move_name" : "Nair",
  "cancel_type" : 2,
  "cancel_name" : "AC",
  "punish_id" : 23,
  "hit_id" : 1,
  "game_frame" : 10386,
  "anim_frame" : 6,
  "damage" : 3.04,
  "opening" : "POKING",
  "kill_dir" : "NEUT"
  }
 ],
 "punishes" : [
  {
  "start_frame" : 305,
  "end_frame" : 373,
  "start_pct" : 0,
  "end_pct" : 4,
  "num_moves" : 1,
  "last_move_id" : 13,
  "last_move_name" : "Nair",
  "opening" : "UNUSED",
  "kill_dir" : "NEUT"
  },
  {
  "start_frame" : 568,
  "end_frame" : 634,
  "start_pct" : 4,
  "end_pct" : 15.94,
  "num_moves" : 2,
  "last_move_id" : 13,
  "last_move_name" : "Nair",
  "opening" : "UNUSED",
  "kill_dir" : "NEUT"
  },
  {
  "start_frame" : 2219,
  "end_frame" : 2300,
  "start_pct" : 15.94,
  "end_pct" : 25.94,
  "num_moves" : 1,
  "last_move_id" : 13,
  "last_move_name" : "Nair",
  "opening" : "UNUSED",
  "kill_dir" : "NEUT"
  },
  {
  "start_frame" : 2305,
  "end_frame" : 2410,
  "start_pct" : 25.94,
  "end_pct" : 35.94,
  "num_moves" : 1,
  "last_move_id" : 9,
  "last_move_name" : "Dtilt",
  "opening" : "UNUSED",
  "kill_dir" : "NEUT"
  },
  {
  "start_frame" : 2818,
  "end_frame" : 3508,
  "start_pct" : 35.94,
  "end_pct" : 125.54,
  "num_moves" : 10,
  "last_move_id" : 17,
  "last_move_name" : "Dair",
  "opening" : "UNUSED",
  "kill_dir" : "DOWN"
  },
  {
  "start_frame" : 4526,
  "end_frame" : 4614,
  "start_pct" : 0,
  "end_pct" : 12,
  "num_moves" : 1,
  "last_move_id" : 8,
  "last_move_name" : "Utilt",
  "opening" : "UNUSED",
  "kill_dir" : "NEUT"
  },
  {
  "start_frame" : 4729,
  "end_frame" : 4761,
  "start_pct" : 12,
  "end_pct" : 22,
  "num_moves" : 1,
  "last_move_id" : 13,
  "last_move_name" : "Nair",
  "opening" : "UNUSED",
  "kill_dir" : "NEUT"
  },
  {
  "start_frame" : 4820,
  "end_frame" : 5177,
  "start_pct" : 22,
  "end_pct" : 50.94,
  "num_moves" : 5,
  "last_move_id" : 3,
  "last_move_name" : "Jab2",
  "opening" : "UNUSED",
  "kill_dir" : "NEUT"
  },
  {
  "start_frame" : 5287,
  "end_frame" : 5484,
  "start_pct" : 50.94,
  "end_pct" : 86.46,
  "num_moves" : 4,
  "last_move_id" : 20,
  "last_move_name" : "UpB",
  "opening" : "UNUSED",
  "kill_dir" : "RIGHT"
  },
  {
  "start_frame" : 6103,
  "end_frame" : 6155,
  "start_pct" : 0,
  "end_pct" : 9.5,
  "num_moves" : 1,
  "last_move_id" : 13,
  "last_move_name" : "Nair",
  "opening" : "UNUSED",
  "kill_dir" : "NEUT"
  },
  {
  "start_frame" : 6164,
  "end_frame" : 6278,
  "start_pct" : 9.5,
  "end_pct" : 21.22,
  "num_moves" : 2,
  "last_move_id" : 13,
  "last_move_name" : "Nair",
  "opening" : "UNUSED",
  "kill_dir" : "NEUT"
  },
  {
  "start_frame" : 6471,
  "end_frame" : 6575,
  "start_pct" : 21.22,
  "end_pct" : 38.48,
  "num_moves" : 2,
  "last_move_id" : 14,
  "last_move_name" : "Fair",
  "opening" : "UNUSED",
  "kill_dir" : "NEUT"
  },
  {
  "start_frame" : 6650,
  "end_frame" : 6698,
  "start_pct" : 38.48,
  "end_pct" : 41.96,
  "num_moves" : 1,
  "last_move_id" : 13,
  "last_move_name" : "Nair",
  "opening" : "UNUSED",
  "kill_dir" : "NEUT"
  },
  {
  "start_frame" : 7042,
  "end_frame" : 7204,
  "start_pct" : 41.96,
  "end_pct" : 64.06,
  "num_moves" : 2,
  "last_move_id" : 16,
  "last_move_name" : "Uair",
  "opening" : "UNUSED",
  "kill_dir" : "NEUT"
  },
  {
  "start_frame" : 7344,
  "end_frame" : 7423,
  "start_pct" : 64.06,
  "end_pct" : 74.06,
  "num_moves" : 1,
  "last_move_id" : 14,
  "last_move_name" : "Fair",
  "opening" : "UNUSED",
  "kill_dir" : "NEUT"
  },
  {
  "start_frame" : 7631,
  "end_frame" : 7722,
  "start_pct" : 74.06,
  "end_pct" : 78.06,
  "num_moves" : 1,
  "last_move_id" : 55,
  "last_move_name" : "Uthrow",
  "opening" : "UNUSED",
  "kill_dir" : "NEUT"
  },
  {
  "start_frame" : 7726,
  "end_frame" : 7949,
  "start_pct" : 78.06,
  "end_pct" : 97.06,
  "num_moves" : 2,
  "last_move_id" : 18,
  "last_move_name" : "NeutB",
  "opening" : "UNUSED",
  "kill_dir" : "DOWN"
  },
  {
  "start_frame" : 8197,
  "end_frame" : 8289,
  "start_pct" : 0,
  "end_pct" : 23.38,
  "num_moves" : 2,
  "last_move_id" : 8,
  "last_move_name" : "Utilt",
  "opening" : "UNUSED",
  "kill_dir" : "NEUT"
  },
  {
  "start_frame" : 8808,
  "end_frame" : 8905,
  "start_pct" : 23.38,
  "end_pct" : 33.38,
  "num_moves" : 1,
  "last_move_id" : 13,
  "last_move_name" : "Nair",
  "opening" : "UNUSED",
  "kill_dir" : "NEUT"
  },
  {
  "start_frame" : 9305,
  "end_frame" : 9565,
  "start_pct" : 33.38,
  "end_pct" : 59.36,
  "num_moves" : 3,
  "last_move_id" : 16,
  "last_move_name" : "Uair",
  "opening" : "UNUSED",
  "kill_dir" : "NEUT"
  },
  {
  "start_frame" : 9705,
  "end_frame" : 9760,
  "start_pct" : 59.36,
  "end_pct" : 68,
  "num_moves" : 1,
  "last_move_id" : 14,
  "last_move_name" : "Fair",
  "opening" : "UNUSED",
  "kill_dir" : "NEUT"
  },
  {
  "start_frame" : 9813,
  "end_frame" : 9864,
  "start_pct" : 68,
  "end_pct" : 71.56,
  "num_moves" : 1,
  "last_move_id" : 13,
  "last_move_name" : "Nair",
  "opening" : "UNUSED",
  "kill_dir" : "NEUT"
  },
  {
  "start_frame" : 9896,
  "end_frame" : 9975,
  "start_pct" : 71.56,
  "end_pct" : 82.44,
  "num_moves" : 2,
  "last_move_id" : 13,
  "last_move_name" : "Nair",
  "opening" : "UNUSED",
  "kill_dir" : "NEUT"
  },
  {
  "start_frame" : 10386,
  "end_frame" : 10432,
  "start_pct" : 82.44,
  "end_pct" : 85.48,
  "num_moves" : 1,
  "last_move_id" : 13,
  "last_move_name" : "Nair",
  "opening" : "UNUSED",
  "kill_dir" : "NEUT"
  }
 ]
 }
]
}

