{
"slippi_version" : "2.0.1",
"parser_version" : "0.5.0",
"analyzer_version" : "0.5.0",
"game_time" : "2019-04-20T19:08:07",
"stage_id" : 31,
"stage_name" : "BATTLE",
"game_length" : 16946,
"players" : [
 {
 "port" : 0,
 "tag_player" : "",
 "tag_css" : "",
 "tag_code" : "",
 "char_id" : 15,
 "char_name" : "JIGGLY",
 "player_type" : 0,
 "cpu_level" : 1,
 "color" : 2,
 "team_id" : 0,
 "start_stocks" : 4,
 "end_stocks" : 1,
 "end_pct" : 73,
 "airdodges" : 3,
 "spotdodges" : 0,
 "rolls" : 7,
 "dashdances" : 24,
 "l_cancels_hit" : 57,
 "l_cancels_missed" : 3,
 "techs" : 0,
 "walltechs" : 0,
 "walljumps" : 0,
 "walltechjumps" : 0,
 "missed_techs" : 2,
 "ledge_grabs" : 3,
 "air_frames" : 11030,
 "wavedashes" : 33,
 "wavelands" : 7,
 "neutral_wins" : 8,
 "pokes" : 34,
 "counters" : 1,
 "powershields" : 12,
 "shield_breaks" : 0,
 "grabs" : 7,
 "grab_escapes" : 0,
 "taunts" : 0,
 "meteor_cancels" : 0,
 "damage_dealt" : 522.491,
 "hits_blocked" : 18,
 "shield_stabs" : 0,
 "edge_cancel_aerials" : 1,
 "edge_cancel_specials" : 0,
 "teeter_cancel_aerials" : 0,
 "teeter_cancel_specials" : 0,
 "phantom_hits" : 0,
 "no_impact_lands" : 0,
 "shield_drops" : 0,
 "pivots" : 1,
 "reverse_edgeguards" : 0,
 "self_destructs" : 0,
 "stage_spikes" : 0,
 "short_hops" : 49,
 "full_hops" : 73,
 "shield_time" : 4459,
 "shield_damage" : 311.402,
 "shield_lowest" : 37.53,
 "total_openings" : 43,
 "mean_kill_openings" : 10.75,
 "mean_kill_percent" : 130.623,
 "mean_opening_percent" : 12.151,
 "galint_ledgedashes" : 0,
 "mean_galint" : 0,
 "interaction_frames" : {
  "EDGEGUARDING" : 1701,
  "TECHCHASING" : 473,
  "PUNISHING" : 545,
  "SHARKING" : 1204,
  "PRESSURING" : 348,
  "OFFENSIVE" : 0,
  "FOOTSIES" : 214,
  "POSITIONING" : 6342,
  "NEUTRAL" : 0,
  "POKING" : 1908,
  "TRADING" : 0,
  "DEFENSIVE" : 0,
  "PRESSURED" : 283,
  "GROUNDING" : 833,
  "PUNISHED" : 826,
  "ESCAPING" : 120,
  "RECOVERING" : 2065
 },
 "interaction_damage" : {
  "EDGEGUARDING" : 42.6,
  "TECHCHASING" : 93.6,
  "PUNISHING" : 53.16,
  "SHARKING" : 0,
  "PRESSURING" : 3,
  "OFFENSIVE" : 0,
  "FOOTSIES" : 0,
  "POSITIONING" : 0,
  "NEUTRAL" : 0,
  "POKING" : 306.971,
  "TRADING" : 0,
  "DEFENSIVE" : 0,
  "PRESSURED" : 0,
  "GROUNDING" : 0,
  "PUNISHED" : 0,
  "ESCAPING" : 0,
  "RECOVERING" : 23.16
 },
 "moves_landed" : {
  "Forward Smash" : 1,
  "Up Smash" : 2,
  "Neutral Air" : 7,
  "Forward Air" : 10,
  "Back Air" : 14,
  "Up Air" : 2,
  "Down Air" : 38,
  "Pummel" : 1,
  "Forward Throw" : 4,
  "Back Throw" : 3,
  "_total" : 82
 },
 "attacks" : [
  {
  "move_id" : 15,
  "move_name" : "Bair",
  "cancel_type" : 1,
  "cancel_name" : "LC",
  "punish_id" : 0,
  "hit_id" : 1,
  "game_frame" : 361,
  "anim_frame" : 9,
  "damage" : 12,
  "opening" : "POKING",
  "kill_dir" : "NEUT"
  },
  {
  "move_id" : 54,
  "move_name" : "Bthrow",
  "cancel_type" : 0,
  "cancel_name" : "",
  "punish_id" : 1,
  "hit_id" : 1,
  "game_frame" : 630,
  "anim_frame" : 23,
  "damage" : 10,
  "opening" : "EDGEGUARDING",
  "kill_dir" : "NEUT"
  },
  {
  "move_id" : 14,
  "move_name" : "Fair",
  "cancel_type" : 0,
  "cancel_name" : "",
  "punish_id" : 1,
  "hit_id" : 1,
  "game_frame" : 797,
  "anim_frame" : 7,
  "damage" : 12,
  "opening" : "POKING",
  "kill_dir" : "NEUT"
  },
  {
  "move_id" : 14,
  "move_name" : "Fair",
  "cancel_type" : 0,
  "cancel_name" : "",
  "punish_id" : 2,
  "hit_id" : 1,
  "game_frame" : 1070,
  "anim_frame" : 7,
  "damage" : 10.92,
  "opening" : "POKING",
  "kill_dir" : "NEUT"
  },
  {
  "move_id" : 13,
  "move_name" : "Nair",
  "cancel_type" : 2,
  "cancel_name" : "AC",
  "punish_id" : 3,
  "hit_id" : 1,
  "game_frame" : 1567,
  "anim_frame" : 20,
  "damage" : 9,
  "opening" : "POKING",
  "kill_dir" : "NEUT"
  },
  {
  "move_id" : 14,
  "move_name" : "Fair",
  "cancel_type" : 1,
  "cancel_name" : "LC",
  "punish_id" : 4,
  "hit_id" : 1,
  "game_frame" : 1689,
  "anim_frame" : 8,
  "damage" : 5.95,
  "opening" : "POKING",
  "kill_dir" : "NEUT"
  },
  {
  "move_id" : 13,
  "move_name" : "Nair",
  "cancel_type" : 1,
  "cancel_name" : "LC",
  "punish_id" : 5,
  "hit_id" : 1,
  "game_frame" : 1827,
  "anim_frame" : 5,
  "damage" : 11.04,
  "opening" : "POKING",
  "kill_dir" : "NEUT"
  },
  {
  "move_id" : 10,
  "move_name" : "Fsmash",
  "cancel_type" : 0,
  "cancel_name" : "",
  "punish_id" : 6,
  "hit_id" : 1,
  "game_frame" : 2131,
  "anim_frame" : 11,
  "damage" : 23.2407,
  "opening" : "POKING",
  "kill_dir" : "RIGHT"
  },
  {
  "move_id" : 13,
  "move_name" : "Nair",
  "cancel_type" : 2,
  "cancel_name" : "AC",
  "punish_id" : 7,
  "hit_id" : 1,
  "game_frame" : 2441,
  "anim_frame" : 8,
  "damage" : 7.74,
  "opening" : "POKING",
  "kill_dir" : "NEUT"
  },
  {
  "move_id" : 17,
  "move_name" : "Dair",
  "cancel_type" : 1,
  "cancel_name" : "LC",
  "punish_id" : 8,
  "hit_id" : 1,
  "game_frame" : 2849,
  "anim_frame" : 4,
  "damage" : 2,
  "opening" : "POKING",
  "kill_dir" : "NEUT"
  },
  {
  "move_id" : 17,
  "move_name" : "Dair",
  "cancel_type" : 1,
  "cancel_name" : "LC",
  "punish_id" : 8,
  "hit_id" : 2,
  "game_frame" : 2854,
  "anim_frame" : 7,
  "damage" : 1.82,
  "opening" : "PUNISHING",
  "kill_dir" : "NEUT"
  },
  {
  "move_id" : 17,
  "move_name" : "Dair",
  "cancel_type" : 1,
  "cancel_name" : "LC",
  "punish_id" : 8,
  "hit_id" : 3,
  "game_frame" : 2859,
  "anim_frame" : 10,
  "damage" : 1.82,
  "opening" : "PUNISHING",
  "kill_dir" : "NEUT"
  },
  {
  "move_id" : 17,
  "move_name" : "Dair",
  "cancel_type" : 1,
  "cancel_name" : "LC",
  "punish_id" : 8,
  "hit_id" : 4,
  "game_frame" : 2864,
  "anim_frame" : 13,
  "damage" : 1.82,
  "opening" : "PUNISHING",
  "kill_dir" : "NEUT"
  },
  {
  "move_id" : 17,
  "move_name" : "Dair",
  "cancel_type" : 1,
  "cancel_name" : "LC",
  "punish_id" : 8,
  "hit_id" : 5,
  "game_frame" : 2869,
  "anim_frame" : 16,
  "damage" : 1.82,
  "opening" : "PUNISHING",
  "kill_dir" : "NEUT"
  },
  {
  "move_id" : 17,
  "move_name" : "Dair",
  "cancel_type" : 1,
  "cancel_name" : "LC",
  "punish_id" : 8,
  "hit_id" : 6,
  "game_frame" : 2874,
  "anim_frame" : 19,
  "damage" : 1.82,
  "opening" : "PUNISHING",
  "kill_dir" : "NEUT"
  },
  {
  "move_id" : 17,
  "move_name" : "Dair",
  "cancel_type" : 1,
  "cancel_name" : "LC",
  "punish_id" : 8,
  "hit_id" : 7,
  "game_frame" : 2879,
  "anim_frame" : 22,
  "damage" : 1.82,
  "opening" : "PUNISHING",
  "kill_dir" : "NEUT"
  },
  {
  "move_id" : 17,
  "move_name" : "Dair",
  "cancel_type" : 1,
  "cancel_name" : "LC",
  "punish_id" : 8,
  "hit_id" : 8,
  "game_frame" : 2885,
  "anim_frame" : 26,
  "damage" : 1.82,
  "opening" : "PUNISHING",
  "kill_dir" : "NEUT"
  },
  {
  "move_id" : 15,
  "move_name" : "Bair",
  "cancel_type" : 2,
  "cancel_name" : "AC",
  "punish_id" : 9,
  "hit_id" : 1,
  "game_frame" : 3355,
  "anim_frame" : 8,
  "damage" : 12,
  "opening" : "RECOVERING",
  "kill_dir" : "NEUT"
  },
  {
  "move_id" : 15,
  "move_name" : "Bair",
  "cancel_type" : 2,
  "cancel_name" : "AC",
  "punish_id" : 10,
  "hit_id" : 1,
  "game_frame" : 3696,
  "anim_frame" : 8,
  "damage" : 10.92,
  "opening" : "POKING",
  "kill_dir" : "NEUT"
  },
  {
  "move_id" : 17,
  "move_name" : "Dair",
  "cancel_type" : 1,
  "cancel_name" : "LC",
  "punish_id" : 11,
  "hit_id" : 1,
  "game_frame" : 3769,
  "anim_frame" : 8,
  "damage" : 1.86,
  "opening" : "POKING",
  "kill_dir" : "NEUT"
  },
  {
  "move_id" : 17,
  "move_name" : "Dair",
  "cancel_type" : 1,
  "cancel_name" : "LC",
  "punish_id" : 11,
  "hit_id" : 2,
  "game_frame" : 3773,
  "anim_frame" : 10,
  "damage" : 1.7,
  "opening" : "PUNISHING",
  "kill_dir" : "NEUT"
  },
  {
  "move_id" : 17,
  "move_name" : "Dair",
  "cancel_type" : 1,
  "cancel_name" : "LC",
  "punish_id" : 11,
  "hit_id" : 3,
  "game_frame" : 3778,
  "anim_frame" : 13,
  "damage" : 1.7,
  "opening" : "PUNISHING",
  "kill_dir" : "NEUT"
  },
  {
  "move_id" : 53,
  "move_name" : "Fthrow",
  "cancel_type" : 0,
  "cancel_name" : "",
  "punish_id" : 11,
  "hit_id" : 1,
  "game_frame" : 3816,
  "anim_frame" : 9,
  "damage" : 12,
  "opening" : "TECHCHASING",
  "kill_dir" : "NEUT"
  },
  {
  "move_id" : 15,
  "move_name" : "Bair",
  "cancel_type" : 0,
  "cancel_name" : "",
  "punish_id" : 11,
  "hit_id" : 1,
  "game_frame" : 3955,
  "anim_frame" : 8,
  "damage" : 10.44,
  "opening" : "TECHCHASING",
  "kill_dir" : "NEUT"
  },
  {
  "move_id" : 14,
  "move_name" : "Fair",
  "cancel_type" : 0,
  "cancel_name" : "",
  "punish_id" : 12,
  "hit_id" : 1,
  "game_frame" : 4862,
  "anim_frame" : 11,
  "damage" : 7,
  "opening" : "POKING",
  "kill_dir" : "NEUT"
  },
  {
  "move_id" : 17,
  "move_name" : "Dair",
  "cancel_type" : 1,
  "cancel_name" : "LC",
  "punish_id" : 13,
  "hit_id" : 1,
  "game_frame" : 5010,
  "anim_frame" : 10,
  "damage" : 2,
  "opening" : "POKING",
  "kill_dir" : "NEUT"
  },
  {
  "move_id" : 17,
  "move_name" : "Dair",
  "cancel_type" : 1,
  "cancel_name" : "LC",
  "punish_id" : 13,
  "hit_id" : 2,
  "game_frame" : 5015,
  "anim_frame" : 13,
  "damage" : 1.82,
  "opening" : "PUNISHING",
  "kill_dir" : "NEUT"
  },
  {
  "move_id" : 13,
  "move_name" : "Nair",
  "cancel_type" : 2,
  "cancel_name" : "AC",
  "punish_id" : 14,
  "hit_id" : 1,
  "game_frame" : 5321,
  "anim_frame" : 25,
  "damage" : 9,
  "opening" : "POKING",
  "kill_dir" : "NEUT"
  },
  {
  "move_id" : 14,
  "move_name" : "Fair",
  "cancel_type" : 0,
  "cancel_name" : "",
  "punish_id" : 14,
  "hit_id" : 1,
  "game_frame" : 5382,
  "anim_frame" : 9,
  "damage" : 6.51,
  "opening" : "POKING",
  "kill_dir" : "NEUT"
  },
  {
  "move_id" : 17,
  "move_name" : "Dair",
  "cancel_type" : 1,
  "cancel_name" : "LC",
  "punish_id" : 15,
  "hit_id" : 1,
  "game_frame" : 5734,
  "anim_frame" : 4,
  "damage" : 1.86,
  "opening" : "POKING",
  "kill_dir" : "NEUT"
  },
  {
  "move_id" : 17,
  "move_name" : "Dair",
  "cancel_type" : 1,
  "cancel_name" : "LC",
  "punish_id" : 15,
  "hit_id" : 2,
  "game_frame" : 5739,
  "anim_frame" : 7,
  "damage" : 1.7,
  "opening" : "PUNISHING",
  "kill_dir" : "NEUT"
  },
  {
  "move_id" : 17,
  "move_name" : "Dair",
  "cancel_type" : 1,
  "cancel_name" : "LC",
  "punish_id" : 15,
  "hit_id" : 3,
  "game_frame" : 5744,
  "anim_frame" : 10,
  "damage" : 1.7,
  "opening" : "PUNISHING",
  "kill_dir" : "NEUT"
  },
  {
  "move_id" : 17,
  "move_name" : "Dair",
  "cancel_type" : 1,
  "cancel_name" : "LC",
  "punish_id" : 15,
  "hit_id" : 4,
  "game_frame" : 5749,
  "anim_frame" : 13,
  "damage" : 1.7,
  "opening" : "PUNISHING",
  "kill_dir" : "NEUT"
  },
  {
  "move_id" : 17,
  "move_name" : "Dair",
  "cancel_type" : 1,
  "cancel_name" : "LC",
  "punish_id" : 15,
  "hit_id" : 5,
  "game_frame" : 5754,
  "anim_frame" : 16,
  "damage" : 1.7,
  "opening" : "PUNISHING",
  "kill_dir" : "NEUT"
  },
  {
  "move_id" : 13,
  "move_name" : "Nair",
  "cancel_type" : 2,
  "cancel_name" : "AC",
  "punish_id" : 16,
  "hit_id" : 1,
  "game_frame" : 6171,
  "anim_frame" : 9,
  "damage" : 8.37,
  "opening" : "POKING",
  "kill_dir" : "NEUT"
  },
  {
  "move_id" : 15,
  "move_name" : "Bair",
  "cancel_type" : 0,
  "cancel_name" : "",
  "punish_id" : 17,
  "hit_id" : 1,
  "game_frame" : 7504,
  "anim_frame" : 9,
  "damage" : 12,
  "opening" : "POKING",
  "kill_dir" : "NEUT"
  },
  {
  "move_id" : 255,
  "move_name" : "(o)",
  "cancel_type" : 0,
  "cancel_name" : "",
  "punish_id" : 17,
  "hit_id" : 1,
  "game_frame" : 7610,
  "anim_frame" : 4,
  "damage" : 1,
  "opening" : "EDGEGUARDING",
  "kill_dir" : "NEUT"
  },
  {
  "move_id" : 16,
  "move_name" : "Uair",
  "cancel_type" : 0,
  "cancel_name" : "",
  "punish_id" : 17,
  "hit_id" : 1,
  "game_frame" : 7705,
  "anim_frame" : 8,
  "damage" : 12,
  "opening" : "EDGEGUARDING",
  "kill_dir" : "UP"
  },
  {
  "move_id" : 15,
  "move_name" : "Bair",
  "cancel_type" : 0,
  "cancel_name" : "",
  "punish_id" : 18,
  "hit_id" : 1,
  "game_frame" : 8488,
  "anim_frame" : 8,
  "damage" : 11.04,
  "opening" : "POKING",
  "kill_dir" : "NEUT"
  },
  {
  "move_id" : 14,
  "move_name" : "Fair",
  "cancel_type" : 1,
  "cancel_name" : "LC",
  "punish_id" : 19,
  "hit_id" : 1,
  "game_frame" : 8654,
  "anim_frame" : 6,
  "damage" : 10,
  "opening" : "POKING",
  "kill_dir" : "NEUT"
  },
  {
  "move_id" : 15,
  "move_name" : "Bair",
  "cancel_type" : 0,
  "cancel_name" : "",
  "punish_id" : 20,
  "hit_id" : 1,
  "game_frame" : 9007,
  "anim_frame" : 9,
  "damage" : 10.32,
  "opening" : "POKING",
  "kill_dir" : "NEUT"
  },
  {
  "move_id" : 15,
  "move_name" : "Bair",
  "cancel_type" : 1,
  "cancel_name" : "LC",
  "punish_id" : 21,
  "hit_id" : 1,
  "game_frame" : 9091,
  "anim_frame" : 9,
  "damage" : 9.48,
  "opening" : "POKING",
  "kill_dir" : "NEUT"
  },
  {
  "move_id" : 14,
  "move_name" : "Fair",
  "cancel_type" : 1,
  "cancel_name" : "LC",
  "punish_id" : 22,
  "hit_id" : 1,
  "game_frame" : 9653,
  "anim_frame" : 6,
  "damage" : 11.16,
  "opening" : "RECOVERING",
  "kill_dir" : "NEUT"
  },
  {
  "move_id" : 14,
  "move_name" : "Fair",
  "cancel_type" : 1,
  "cancel_name" : "LC",
  "punish_id" : 22,
  "hit_id" : 1,
  "game_frame" : 9715,
  "anim_frame" : 7,
  "damage" : 10.2,
  "opening" : "EDGEGUARDING",
  "kill_dir" : "NEUT"
  },
  {
  "move_id" : 13,
  "move_name" : "Nair",
  "cancel_type" : 2,
  "cancel_name" : "AC",
  "punish_id" : 23,
  "hit_id" : 1,
  "game_frame" : 9941,
  "anim_frame" : 26,
  "damage" : 9,
  "opening" : "POKING",
  "kill_dir" : "NEUT"
  },
  {
  "move_id" : 53,
  "move_name" : "Fthrow",
  "cancel_type" : 0,
  "cancel_name" : "",
  "punish_id" : 24,
  "hit_id" : 1,
  "game_frame" : 10007,
  "anim_frame" : 9,
  "damage" : 12,
  "opening" : "TECHCHASING",
  "kill_dir" : "NEUT"
  },
  {
  "move_id" : 15,
  "move_name" : "Bair",
  "cancel_type" : 1,
  "cancel_name" : "LC",
  "punish_id" : 25,
  "hit_id" : 1,
  "game_frame" : 10713,
  "anim_frame" : 8,
  "damage" : 10.68,
  "opening" : "POKING",
  "kill_dir" : "NEUT"
  },
  {
  "move_id" : 53,
  "move_name" : "Fthrow",
  "cancel_type" : 0,
  "cancel_name" : "",
  "punish_id" : 26,
  "hit_id" : 1,
  "game_frame" : 10817,
  "anim_frame" : 9,
  "damage" : 11.04,
  "opening" : "TECHCHASING",
  "kill_dir" : "NEUT"
  },
  {
  "move_id" : 17,
  "move_name" : "Dair",
  "cancel_type" : 1,
  "cancel_name" : "LC",
  "punish_id" : 27,
  "hit_id" : 1,
  "game_frame" : 11564,
  "anim_frame" : 4,
  "damage" : 2,
  "opening" : "POKING",
  "kill_dir" : "NEUT"
  },
  {
  "move_id" : 17,
  "move_name" : "Dair",
  "cancel_type" : 1,
  "cancel_name" : "LC",
  "punish_id" : 27,
  "hit_id" : 2,
  "game_frame" : 11569,
  "anim_frame" : 7,
  "damage" : 1.82,
  "opening" : "PUNISHING",
  "kill_dir" : "NEUT"
  },
  {
  "move_id" : 17,
  "move_name" : "Dair",
  "cancel_type" : 1,
  "cancel_name" : "LC",
  "punish_id" : 27,
  "hit_id" : 3,
  "game_frame" : 11574,
  "anim_frame" : 10,
  "damage" : 1.82,
  "opening" : "PUNISHING",
  "kill_dir" : "NEUT"
  },
  {
  "move_id" : 17,
  "move_name" : "Dair",
  "cancel_type" : 1,
  "cancel_name" : "LC",
  "punish_id" : 27,
  "hit_id" : 4,
  "game_frame" : 11579,
  "anim_frame" : 13,
  "damage" : 1.82,
  "opening" : "PUNISHING",
  "kill_dir" : "NEUT"
  },
  {
  "move_id" : 17,
  "move_name" : "Dair",
  "cancel_type" : 1,
  "cancel_name" : "LC",
  "punish_id" : 27,
  "hit_id" : 5,
  "game_frame" : 11584,
  "anim_frame" : 16,
  "damage" : 1.82,
  "opening" : "PUNISHING",
  "kill_dir" : "NEUT"
  },
  {
  "move_id" : 17,
  "move_name" : "Dair",
  "cancel_type" : 1,
  "cancel_name" : "LC",
  "punish_id" : 27,
  "hit_id" : 6,
  "game_frame" : 11589,
  "anim_frame" : 19,
  "damage" : 1.82,
  "opening" : "PUNISHING",
  "kill_dir" : "NEUT"
  },
  {
  "move_id" : 17,
  "move_name" : "Dair",
  "cancel_type" : 1,
  "cancel_name" : "LC",
  "punish_id" : 27,
  "hit_id" : 7,
  "game_frame" : 11594,
  "anim_frame" : 22,
  "damage" : 1.82,
  "opening" : "PUNISHING",
  "kill_dir" : "NEUT"
  },
  {
  "move_id" : 11,
  "move_name" : "Usmash",
  "cancel_type" : 0,
  "cancel_name" : "",
  "punish_id" : 27,
  "hit_id" : 1,
  "game_frame" : 11622,
  "anim_frame" : 9,
  "damage" : 14,
  "opening" : "PUNISHING",
  "kill_dir" : "UP"
  },
  {
  "move_id" : 54,
  "move_name" : "Bthrow",
  "cancel_type" : 0,
  "cancel_name" : "",
  "punish_id" : 28,
  "hit_id" : 1,
  "game_frame" : 12785,
  "anim_frame" : 23,
  "damage" : 10,
  "opening" : "TECHCHASING",
  "kill_dir" : "NEUT"
  },
  {
  "move_id" : 17,
  "move_name" : "Dair",
  "cancel_type" : 1,
  "cancel_name" : "LC",
  "punish_id" : 29,
  "hit_id" : 1,
  "game_frame" : 12990,
  "anim_frame" : 4,
  "damage" : 2,
  "opening" : "POKING",
  "kill_dir" : "NEUT"
  },
  {
  "move_id" : 17,
  "move_name" : "Dair",
  "cancel_type" : 1,
  "cancel_name" : "LC",
  "punish_id" : 29,
  "hit_id" : 2,
  "game_frame" : 12996,
  "anim_frame" : 8,
  "damage" : 1.82,
  "opening" : "PUNISHING",
  "kill_dir" : "NEUT"
  },
  {
  "move_id" : 15,
  "move_name" : "Bair",
  "cancel_type" : 1,
  "cancel_name" : "LC",
  "punish_id" : 30,
  "hit_id" : 1,
  "game_frame" : 13078,
  "anim_frame" : 9,
  "damage" : 12,
  "opening" : "POKING",
  "kill_dir" : "NEUT"
  },
  {
  "move_id" : 15,
  "move_name" : "Bair",
  "cancel_type" : 2,
  "cancel_name" : "AC",
  "punish_id" : 31,
  "hit_id" : 1,
  "game_frame" : 13116,
  "anim_frame" : 8,
  "damage" : 10.92,
  "opening" : "POKING",
  "kill_dir" : "NEUT"
  },
  {
  "move_id" : 54,
  "move_name" : "Bthrow",
  "cancel_type" : 0,
  "cancel_name" : "",
  "punish_id" : 32,
  "hit_id" : 1,
  "game_frame" : 13269,
  "anim_frame" : 23,
  "damage" : 9.4,
  "opening" : "EDGEGUARDING",
  "kill_dir" : "NEUT"
  },
  {
  "move_id" : 15,
  "move_name" : "Bair",
  "cancel_type" : 1,
  "cancel_name" : "LC",
  "punish_id" : 33,
  "hit_id" : 1,
  "game_frame" : 13925,
  "anim_frame" : 10,
  "damage" : 10.2,
  "opening" : "POKING",
  "kill_dir" : "NEUT"
  },
  {
  "move_id" : 13,
  "move_name" : "Nair",
  "cancel_type" : 2,
  "cancel_name" : "AC",
  "punish_id" : 34,
  "hit_id" : 1,
  "game_frame" : 14280,
  "anim_frame" : 11,
  "damage" : 9,
  "opening" : "POKING",
  "kill_dir" : "NEUT"
  },
  {
  "move_id" : 52,
  "move_name" : "Pummel",
  "cancel_type" : 0,
  "cancel_name" : "",
  "punish_id" : 35,
  "hit_id" : 1,
  "game_frame" : 14696,
  "anim_frame" : 9,
  "damage" : 3,
  "opening" : "PRESSURING",
  "kill_dir" : "NEUT"
  },
  {
  "move_id" : 53,
  "move_name" : "Fthrow",
  "cancel_type" : 0,
  "cancel_name" : "",
  "punish_id" : 35,
  "hit_id" : 1,
  "game_frame" : 14729,
  "anim_frame" : 9,
  "damage" : 12,
  "opening" : "TECHCHASING",
  "kill_dir" : "NEUT"
  },
  {
  "move_id" : 16,
  "move_name" : "Uair",
  "cancel_type" : 0,
  "cancel_name" : "",
  "punish_id" : 35,
  "hit_id" : 1,
  "game_frame" : 14849,
  "anim_frame" : 8,
  "damage" : 12,
  "opening" : "POKING",
  "kill_dir" : "NEUT"
  },
  {
  "move_id" : 14,
  "move_name" : "Fair",
  "cancel_type" : 1,
  "cancel_name" : "LC",
  "punish_id" : 36,
  "hit_id" : 1,
  "game_frame" : 15034,
  "anim_frame" : 10,
  "damage" : 7,
  "opening" : "POKING",
  "kill_dir" : "NEUT"
  },
  {
  "move_id" : 14,
  "move_name" : "Fair",
  "cancel_type" : 1,
  "cancel_name" : "LC",
  "punish_id" : 37,
  "hit_id" : 1,
  "game_frame" : 15170,
  "anim_frame" : 6,
  "damage" : 10.92,
  "opening" : "POKING",
  "kill_dir" : "NEUT"
  },
  {
  "move_id" : 15,
  "move_name" : "Bair",
  "cancel_type" : 2,
  "cancel_name" : "AC",
  "punish_id" : 38,
  "hit_id" : 1,
  "game_frame" : 15626,
  "anim_frame" : 8,
  "damage" : 11.52,
  "opening" : "POKING",
  "kill_dir" : "NEUT"
  },
  {
  "move_id" : 17,
  "move_name" : "Dair",
  "cancel_type" : 1,
  "cancel_name" : "LC",
  "punish_id" : 39,
  "hit_id" : 1,
  "game_frame" : 15918,
  "anim_frame" : 7,
  "damage" : 2,
  "opening" : "POKING",
  "kill_dir" : "NEUT"
  },
  {
  "move_id" : 17,
  "move_name" : "Dair",
  "cancel_type" : 1,
  "cancel_name" : "LC",
  "punish_id" : 39,
  "hit_id" : 2,
  "game_frame" : 15923,
  "anim_frame" : 10,
  "damage" : 1.82,
  "opening" : "TECHCHASING",
  "kill_dir" : "NEUT"
  },
  {
  "move_id" : 17,
  "move_name" : "Dair",
  "cancel_type" : 1,
  "cancel_name" : "LC",
  "punish_id" : 39,
  "hit_id" : 3,
  "game_frame" : 15931,
  "anim_frame" : 16,
  "damage" : 1.82,
  "opening" : "TECHCHASING",
  "kill_dir" : "NEUT"
  },
  {
  "move_id" : 17,
  "move_name" : "Dair",
  "cancel_type" : 1,
  "cancel_name" : "LC",
  "punish_id" : 39,
  "hit_id" : 4,
  "game_frame" : 15936,
  "anim_frame" : 19,
  "damage" : 1.82001,
  "opening" : "TECHCHASING",
  "kill_dir" : "NEUT"
  },
  {
  "move_id" : 17,
  "move_name" : "Dair",
  "cancel_type" : 1,
  "cancel_name" : "LC",
  "punish_id" : 39,
  "hit_id" : 5,
  "game_frame" : 15941,
  "anim_frame" : 22,
  "damage" : 1.82001,
  "opening" : "TECHCHASING",
  "kill_dir" : "NEUT"
  },
  {
  "move_id" : 17,
  "move_name" : "Dair",
  "cancel_type" : 1,
  "cancel_name" : "LC",
  "punish_id" : 40,
  "hit_id" : 1,
  "game_frame" : 15999,
  "anim_frame" : 8,
  "damage" : 1.82001,
  "opening" : "POKING",
  "kill_dir" : "NEUT"
  },
  {
  "move_id" : 17,
  "move_name" : "Dair",
  "cancel_type" : 1,
  "cancel_name" : "LC",
  "punish_id" : 40,
  "hit_id" : 2,
  "game_frame" : 16003,
  "anim_frame" : 10,
  "damage" : 1.66,
  "opening" : "PUNISHING",
  "kill_dir" : "NEUT"
  },
  {
  "move_id" : 17,
  "move_name" : "Dair",
  "cancel_type" : 1,
  "cancel_name" : "LC",
  "punish_id" : 40,
  "hit_id" : 3,
  "game_frame" : 16008,
  "anim_frame" : 13,
  "damage" : 1.66,
  "opening" : "TECHCHASING",
  "kill_dir" : "NEUT"
  },
  {
  "move_id" : 17,
  "move_name" : "Dair",
  "cancel_type" : 1,
  "cancel_name" : "LC",
  "punish_id" : 40,
  "hit_id" : 4,
  "game_frame" : 16013,
  "anim_frame" : 16,
  "damage" : 1.66,
  "opening" : "TECHCHASING",
  "kill_dir" : "NEUT"
  },
  {
  "move_id" : 17,
  "move_name" : "Dair",
  "cancel_type" : 1,
  "cancel_name" : "LC",
  "punish_id" : 41,
  "hit_id" : 1,
  "game_frame" : 16723,
  "anim_frame" : 4,
  "damage" : 1.66,
  "opening" : "POKING",
  "kill_dir" : "NEUT"
  },
  {
  "move_id" : 17,
  "move_name" : "Dair",
  "cancel_type" : 1,
  "cancel_name" : "LC",
  "punish_id" : 41,
  "hit_id" : 2,
  "game_frame" : 16746,
  "anim_frame" : 25,
  "damage" : 1.52,
  "opening" : "TECHCHASING",
  "kill_dir" : "NEUT"
  },
  {
  "move_id" : 11,
  "move_name" : "Usmash",
  "cancel_type" : 0,
  "cancel_name" : "",
  "punish_id" : 41,
  "hit_id" : 1,
  "game_frame" : 16779,
  "anim_frame" : 6,
  "damage" : 14,
  "opening" : "TECHCHASING",
  "kill_dir" : "UP"
  }
 ],
 "punishes" : [
  {
  "start_frame" : 361,
  "end_frame" : 412,
  "start_pct" : 0,
  "end_pct" : 12,
  "num_moves" : 1,
  "last_move_id" : 15,
  "last_move_name" : "Bair",
  "opening" : "UNUSED",
  "kill_dir" : "NEUT"
  },
  {
  "start_frame" : 630,
  "end_frame" : 858,
  "start_pct" : 12,
  "end_pct" : 34,
  "num_moves" : 2,
  "last_move_id" : 14,
  "last_move_name" : "Fair",
  "opening" : "UNUSED",
  "kill_dir" : "NEUT"
  },
  {
  "start_frame" : 1070,
  "end_frame" : 1158,
  "start_pct" : 34,
  "end_pct" : 44.92,
  "num_moves" : 1,
  "last_move_id" : 14,
  "last_move_name" : "Fair",
  "opening" : "UNUSED",
  "kill_dir" : "NEUT"
  },
  {
  "start_frame" : 1567,
  "end_frame" : 1626,
  "start_pct" : 44.92,
  "end_pct" : 53.92,
  "num_moves" : 1,
  "last_move_id" : 13,
  "last_move_name" : "Nair",
  "opening" : "UNUSED",
  "kill_dir" : "NEUT"
  },
  {
  "start_frame" : 1689,
  "end_frame" : 1721,
  "start_pct" : 53.92,
  "end_pct" : 59.87,
  "num_moves" : 1,
  "last_move_id" : 14,
  "last_move_name" : "Fair",
  "opening" : "UNUSED",
  "kill_dir" : "NEUT"
  },
  {
  "start_frame" : 1827,
  "end_frame" : 1969,
  "start_pct" : 59.87,
  "end_pct" : 70.91,
  "num_moves" : 1,
  "last_move_id" : 13,
  "last_move_name" : "Nair",
  "opening" : "UNUSED",
  "kill_dir" : "NEUT"
  },
  {
  "start_frame" : 2131,
  "end_frame" : 2200,
  "start_pct" : 70.91,
  "end_pct" : 94.1507,
  "num_moves" : 1,
  "last_move_id" : 10,
  "last_move_name" : "Fsmash",
  "opening" : "UNUSED",
  "kill_dir" : "RIGHT"
  },
  {
  "start_frame" : 2441,
  "end_frame" : 2485,
  "start_pct" : 0,
  "end_pct" : 7.74,
  "num_moves" : 1,
  "last_move_id" : 13,
  "last_move_name" : "Nair",
  "opening" : "UNUSED",
  "kill_dir" : "NEUT"
  },
  {
  "start_frame" : 2849,
  "end_frame" : 2933,
  "start_pct" : 7.74,
  "end_pct" : 22.48,
  "num_moves" : 8,
  "last_move_id" : 17,
  "last_move_name" : "Dair",
  "opening" : "UNUSED",
  "kill_dir" : "NEUT"
  },
  {
  "start_frame" : 3355,
  "end_frame" : 3416,
  "start_pct" : 22.48,
  "end_pct" : 34.48,
  "num_moves" : 1,
  "last_move_id" : 15,
  "last_move_name" : "Bair",
  "opening" : "UNUSED",
  "kill_dir" : "NEUT"
  },
  {
  "start_frame" : 3696,
  "end_frame" : 3762,
  "start_pct" : 34.48,
  "end_pct" : 45.4,
  "num_moves" : 1,
  "last_move_id" : 15,
  "last_move_name" : "Bair",
  "opening" : "UNUSED",
  "kill_dir" : "NEUT"
  },
  {
  "start_frame" : 3769,
  "end_frame" : 4063,
  "start_pct" : 45.4,
  "end_pct" : 73.1,
  "num_moves" : 5,
  "last_move_id" : 15,
  "last_move_name" : "Bair",
  "opening" : "UNUSED",
  "kill_dir" : "NEUT"
  },
  {
  "start_frame" : 4862,
  "end_frame" : 4916,
  "start_pct" : 73.1,
  "end_pct" : 80.1,
  "num_moves" : 1,
  "last_move_id" : 14,
  "last_move_name" : "Fair",
  "opening" : "UNUSED",
  "kill_dir" : "NEUT"
  },
  {
  "start_frame" : 5010,
  "end_frame" : 5096,
  "start_pct" : 80.1,
  "end_pct" : 83.92,
  "num_moves" : 2,
  "last_move_id" : 17,
  "last_move_name" : "Dair",
  "opening" : "UNUSED",
  "kill_dir" : "NEUT"
  },
  {
  "start_frame" : 5321,
  "end_frame" : 5459,
  "start_pct" : 83.92,
  "end_pct" : 99.43,
  "num_moves" : 2,
  "last_move_id" : 14,
  "last_move_name" : "Fair",
  "opening" : "UNUSED",
  "kill_dir" : "NEUT"
  },
  {
  "start_frame" : 5734,
  "end_frame" : 5814,
  "start_pct" : 99.43,
  "end_pct" : 108.09,
  "num_moves" : 5,
  "last_move_id" : 17,
  "last_move_name" : "Dair",
  "opening" : "UNUSED",
  "kill_dir" : "NEUT"
  },
  {
  "start_frame" : 6171,
  "end_frame" : 6295,
  "start_pct" : 108.09,
  "end_pct" : 116.46,
  "num_moves" : 1,
  "last_move_id" : 13,
  "last_move_name" : "Nair",
  "opening" : "UNUSED",
  "kill_dir" : "NEUT"
  },
  {
  "start_frame" : 7504,
  "end_frame" : 7793,
  "start_pct" : 116.46,
  "end_pct" : 141.46,
  "num_moves" : 3,
  "last_move_id" : 16,
  "last_move_name" : "Uair",
  "opening" : "UNUSED",
  "kill_dir" : "UP"
  },
  {
  "start_frame" : 8488,
  "end_frame" : 8543,
  "start_pct" : 0,
  "end_pct" : 11.04,
  "num_moves" : 1,
  "last_move_id" : 15,
  "last_move_name" : "Bair",
  "opening" : "UNUSED",
  "kill_dir" : "NEUT"
  },
  {
  "start_frame" : 8654,
  "end_frame" : 8707,
  "start_pct" : 11.04,
  "end_pct" : 21.04,
  "num_moves" : 1,
  "last_move_id" : 14,
  "last_move_name" : "Fair",
  "opening" : "UNUSED",
  "kill_dir" : "NEUT"
  },
  {
  "start_frame" : 9007,
  "end_frame" : 9065,
  "start_pct" : 21.04,
  "end_pct" : 31.36,
  "num_moves" : 1,
  "last_move_id" : 15,
  "last_move_name" : "Bair",
  "opening" : "UNUSED",
  "kill_dir" : "NEUT"
  },
  {
  "start_frame" : 9091,
  "end_frame" : 9277,
  "start_pct" : 31.36,
  "end_pct" : 40.84,
  "num_moves" : 1,
  "last_move_id" : 15,
  "last_move_name" : "Bair",
  "opening" : "UNUSED",
  "kill_dir" : "NEUT"
  },
  {
  "start_frame" : 9653,
  "end_frame" : 9864,
  "start_pct" : 40.84,
  "end_pct" : 62.2,
  "num_moves" : 2,
  "last_move_id" : 14,
  "last_move_name" : "Fair",
  "opening" : "UNUSED",
  "kill_dir" : "NEUT"
  },
  {
  "start_frame" : 9941,
  "end_frame" : 9975,
  "start_pct" : 62.2,
  "end_pct" : 71.2,
  "num_moves" : 1,
  "last_move_id" : 13,
  "last_move_name" : "Nair",
  "opening" : "UNUSED",
  "kill_dir" : "NEUT"
  },
  {
  "start_frame" : 10007,
  "end_frame" : 10223,
  "start_pct" : 71.2,
  "end_pct" : 83.2,
  "num_moves" : 1,
  "last_move_id" : 53,
  "last_move_name" : "Fthrow",
  "opening" : "UNUSED",
  "kill_dir" : "NEUT"
  },
  {
  "start_frame" : 10713,
  "end_frame" : 10779,
  "start_pct" : 83.2,
  "end_pct" : 93.88,
  "num_moves" : 1,
  "last_move_id" : 15,
  "last_move_name" : "Bair",
  "opening" : "UNUSED",
  "kill_dir" : "NEUT"
  },
  {
  "start_frame" : 10817,
  "end_frame" : 11061,
  "start_pct" : 93.88,
  "end_pct" : 104.92,
  "num_moves" : 1,
  "last_move_id" : 53,
  "last_move_name" : "Fthrow",
  "opening" : "UNUSED",
  "kill_dir" : "NEUT"
  },
  {
  "start_frame" : 11564,
  "end_frame" : 11697,
  "start_pct" : 104.92,
  "end_pct" : 131.84,
  "num_moves" : 8,
  "last_move_id" : 11,
  "last_move_name" : "Usmash",
  "opening" : "UNUSED",
  "kill_dir" : "UP"
  },
  {
  "start_frame" : 12785,
  "end_frame" : 12935,
  "start_pct" : 0,
  "end_pct" : 10,
  "num_moves" : 1,
  "last_move_id" : 54,
  "last_move_name" : "Bthrow",
  "opening" : "UNUSED",
  "kill_dir" : "NEUT"
  },
  {
  "start_frame" : 12990,
  "end_frame" : 13067,
  "start_pct" : 10,
  "end_pct" : 13.82,
  "num_moves" : 2,
  "last_move_id" : 17,
  "last_move_name" : "Dair",
  "opening" : "UNUSED",
  "kill_dir" : "NEUT"
  },
  {
  "start_frame" : 13078,
  "end_frame" : 13110,
  "start_pct" : 13.82,
  "end_pct" : 25.82,
  "num_moves" : 1,
  "last_move_id" : 15,
  "last_move_name" : "Bair",
  "opening" : "UNUSED",
  "kill_dir" : "NEUT"
  },
  {
  "start_frame" : 13116,
  "end_frame" : 13150,
  "start_pct" : 25.82,
  "end_pct" : 36.74,
  "num_moves" : 1,
  "last_move_id" : 15,
  "last_move_name" : "Bair",
  "opening" : "UNUSED",
  "kill_dir" : "NEUT"
  },
  {
  "start_frame" : 13269,
  "end_frame" : 13372,
  "start_pct" : 36.74,
  "end_pct" : 46.14,
  "num_moves" : 1,
  "last_move_id" : 54,
  "last_move_name" : "Bthrow",
  "opening" : "UNUSED",
  "kill_dir" : "NEUT"
  },
  {
  "start_frame" : 13925,
  "end_frame" : 14040,
  "start_pct" : 46.14,
  "end_pct" : 56.34,
  "num_moves" : 1,
  "last_move_id" : 15,
  "last_move_name" : "Bair",
  "opening" : "UNUSED",
  "kill_dir" : "NEUT"
  },
  {
  "start_frame" : 14280,
  "end_frame" : 14342,
  "start_pct" : 56.34,
  "end_pct" : 65.34,
  "num_moves" : 1,
  "last_move_id" : 13,
  "last_move_name" : "Nair",
  "opening" : "UNUSED",
  "kill_dir" : "NEUT"
  },
  {
  "start_frame" : 14696,
  "end_frame" : 15010,
  "start_pct" : 65.34,
  "end_pct" : 92.34,
  "num_moves" : 3,
  "last_move_id" : 16,
  "last_move_name" : "Uair",
  "opening" : "UNUSED",
  "kill_dir" : "NEUT"
  },
  {
  "start_frame" : 15034,
  "end_frame" : 15126,
  "start_pct" : 92.34,
  "end_pct" : 99.34,
  "num_moves" : 1,
  "last_move_id" : 14,
  "last_move_name" : "Fair",
  "opening" : "UNUSED",
  "kill_dir" : "NEUT"
  },
  {
  "start_frame" : 15170,
  "end_frame" : 15452,
  "start_pct" : 99.34,
  "end_pct" : 110.26,
  "num_moves" : 1,
  "last_move_id" : 14,
  "last_move_name" : "Fair",
  "opening" : "UNUSED",
  "kill_dir" : "NEUT"
  },
  {
  "start_frame" : 15626,
  "end_frame" : 15893,
  "start_pct" : 110.26,
  "end_pct" : 121.78,
  "num_moves" : 1,
  "last_move_id" : 15,
  "last_move_name" : "Bair",
  "opening" : "UNUSED",
  "kill_dir" : "NEUT"
  },
  {
  "start_frame" : 15918,
  "end_frame" : 15990,
  "start_pct" : 121.78,
  "end_pct" : 131.06,
  "num_moves" : 5,
  "last_move_id" : 17,
  "last_move_name" : "Dair",
  "opening" : "UNUSED",
  "kill_dir" : "NEUT"
  },
  {
  "start_frame" : 15999,
  "end_frame" : 16083,
  "start_pct" : 131.06,
  "end_pct" : 137.86,
  "num_moves" : 4,
  "last_move_id" : 17,
  "last_move_name" : "Dair",
  "opening" : "UNUSED",
  "kill_dir" : "NEUT"
  },
  {
  "start_frame" : 16723,
  "end_frame" : 16843,
  "start_pct" : 137.86,
  "end_pct" : 155.04,
  "num_moves" : 3,
  "last_move_id" : 11,
  "last_move_name" : "Usmash",
  "opening" : "UNUSED",
  "kill_dir" : "UP"
  }
 ]
 },
 {
 "port" : 3,
 "tag_player" : "",
 "tag_css" : "",
 "tag_code" : "",
 "char_id" : 15,
 "char_name" : "JIGGLY",
 "player_type" : 0,
 "cpu_level" : 1,
 "color" : 3,
 "team_id" : 0,
 "start_stocks" : 4,
 "end_stocks" : 0,
 "end_pct" : 155,
 "airdodges" : 1,
 "spotdodges" : 0,
 "rolls" : 1,
 "dashdances" : 1,
 "l_cancels_hit" : 26,
 "l_cancels_missed" : 12,
 "techs" : 1,
 "walltechs" : 0,
 "walljumps" : 0,
 "walltechjumps" : 0,
 "missed_techs" : 8,
 "ledge_grabs" : 2,
 "air_frames" : 11327,
 "wavedashes" : 9,
 "wavelands" : 0,
 "neutral_wins" : 9,
 "pokes" : 26,
 "counters" : 1,
 "powershields" : 20,
 "shield_breaks" : 0,
 "grabs" : 5,
 "grab_escapes" : 0,
 "taunts" : 0,
 "meteor_cancels" : 0,
 "damage_dealt" : 462.34,
 "hits_blocked" : 23,
 "shield_stabs" : 3,
 "edge_cancel_aerials" : 0,
 "edge_cancel_specials" : 0,
 "teeter_cancel_aerials" : 0,
 "teeter_cancel_specials" : 0,
 "phantom_hits" : 0,
 "no_impact_lands" : 0,
 "shield_drops" : 1,
 "pivots" : 0,
 "reverse_edgeguards" : 0,
 "self_destructs" : 0,
 "stage_spikes" : 0,
 "short_hops" : 90,
 "full_hops" : 21,
 "shield_time" : 4124,
 "shield_damage" : 287.86,
 "shield_lowest" : 41.59,
 "total_openings" : 36,
 "mean_kill_openings" : 12,
 "mean_kill_percent" : 154.113,
 "mean_opening_percent" : 12.8428,
 "galint_ledgedashes" : 0,
 "mean_galint" : 0,
 "interaction_frames" : {
  "EDGEGUARDING" : 2065,
  "TECHCHASING" : 120,
  "PUNISHING" : 826,
  "SHARKING" : 833,
  "PRESSURING" : 283,
  "OFFENSIVE" : 0,
  "FOOTSIES" : 214,
  "POSITIONING" : 6342,
  "NEUTRAL" : 0,
  "POKING" : 1908,
  "TRADING" : 0,
  "DEFENSIVE" : 0,
  "PRESSURED" : 348,
  "GROUNDING" : 1204,
  "PUNISHED" : 545,
  "ESCAPING" : 473,
  "RECOVERING" : 1701
 },
 "interaction_damage" : {
  "EDGEGUARDING" : 30.16,
  "TECHCHASING" : 58.92,
  "PUNISHING" : 97.2,
  "SHARKING" : 30.3,
  "PRESSURING" : 0,
  "OFFENSIVE" : 0,
  "FOOTSIES" : 0,
  "POSITIONING" : 0,
  "NEUTRAL" : 0,
  "POKING" : 208.74,
  "TRADING" : 0,
  "DEFENSIVE" : 0,
  "PRESSURED" : 0,
  "GROUNDING" : 0,
  "PUNISHED" : 0,
  "ESCAPING" : 0,
  "RECOVERING" : 37.02
 },
 "moves_landed" : {
  "Up Smash" : 2,
  "Neutral Air" : 11,
  "Forward Air" : 10,
  "Back Air" : 19,
  "Up Air" : 1,
  "Down Air" : 22,
  "Forward Throw" : 5,
  "_total" : 70
 },
 "attacks" : [
  {
  "move_id" : 13,
  "move_name" : "Nair",
  "cancel_type" : 0,
  "cancel_name" : "",
  "punish_id" : 0,
  "hit_id" : 1,
  "game_frame" : 361,
  "anim_frame" : 14,
  "damage" : 9,
  "opening" : "POKING",
  "kill_dir" : "NEUT"
  },
  {
  "move_id" : 13,
  "move_name" : "Nair",
  "cancel_type" : 2,
  "cancel_name" : "AC",
  "punish_id" : 1,
  "hit_id" : 1,
  "game_frame" : 560,
  "anim_frame" : 21,
  "damage" : 8.19,
  "opening" : "POKING",
  "kill_dir" : "NEUT"
  },
  {
  "move_id" : 13,
  "move_name" : "Nair",
  "cancel_type" : 0,
  "cancel_name" : "",
  "punish_id" : 2,
  "hit_id" : 1,
  "game_frame" : 797,
  "anim_frame" : 12,
  "damage" : 7.47,
  "opening" : "POKING",
  "kill_dir" : "NEUT"
  },
  {
  "move_id" : 15,
  "move_name" : "Bair",
  "cancel_type" : 2,
  "cancel_name" : "AC",
  "punish_id" : 3,
  "hit_id" : 1,
  "game_frame" : 1382,
  "anim_frame" : 9,
  "damage" : 12,
  "opening" : "POKING",
  "kill_dir" : "NEUT"
  },
  {
  "move_id" : 15,
  "move_name" : "Bair",
  "cancel_type" : 0,
  "cancel_name" : "",
  "punish_id" : 3,
  "hit_id" : 1,
  "game_frame" : 1442,
  "anim_frame" : 9,
  "damage" : 10.92,
  "opening" : "SHARKING",
  "kill_dir" : "NEUT"
  },
  {
  "move_id" : 53,
  "move_name" : "Fthrow",
  "cancel_type" : 0,
  "cancel_name" : "",
  "punish_id" : 4,
  "hit_id" : 1,
  "game_frame" : 1758,
  "anim_frame" : 9,
  "damage" : 12,
  "opening" : "TECHCHASING",
  "kill_dir" : "NEUT"
  },
  {
  "move_id" : 13,
  "move_name" : "Nair",
  "cancel_type" : 2,
  "cancel_name" : "AC",
  "punish_id" : 5,
  "hit_id" : 1,
  "game_frame" : 1907,
  "anim_frame" : 7,
  "damage" : 7.65,
  "opening" : "POKING",
  "kill_dir" : "NEUT"
  },
  {
  "move_id" : 17,
  "move_name" : "Dair",
  "cancel_type" : 0,
  "cancel_name" : "",
  "punish_id" : 6,
  "hit_id" : 1,
  "game_frame" : 2477,
  "anim_frame" : 4,
  "damage" : 2,
  "opening" : "POKING",
  "kill_dir" : "NEUT"
  },
  {
  "move_id" : 17,
  "move_name" : "Dair",
  "cancel_type" : 0,
  "cancel_name" : "",
  "punish_id" : 6,
  "hit_id" : 2,
  "game_frame" : 2482,
  "anim_frame" : 7,
  "damage" : 1.82,
  "opening" : "PUNISHING",
  "kill_dir" : "NEUT"
  },
  {
  "move_id" : 53,
  "move_name" : "Fthrow",
  "cancel_type" : 0,
  "cancel_name" : "",
  "punish_id" : 6,
  "hit_id" : 1,
  "game_frame" : 2540,
  "anim_frame" : 9,
  "damage" : 12,
  "opening" : "TECHCHASING",
  "kill_dir" : "NEUT"
  },
  {
  "move_id" : 53,
  "move_name" : "Fthrow",
  "cancel_type" : 0,
  "cancel_name" : "",
  "punish_id" : 7,
  "hit_id" : 1,
  "game_frame" : 2929,
  "anim_frame" : 9,
  "damage" : 10.92,
  "opening" : "TECHCHASING",
  "kill_dir" : "NEUT"
  },
  {
  "move_id" : 15,
  "move_name" : "Bair",
  "cancel_type" : 2,
  "cancel_name" : "AC",
  "punish_id" : 8,
  "hit_id" : 1,
  "game_frame" : 3074,
  "anim_frame" : 8,
  "damage" : 12,
  "opening" : "POKING",
  "kill_dir" : "NEUT"
  },
  {
  "move_id" : 255,
  "move_name" : "(o)",
  "cancel_type" : 0,
  "cancel_name" : "",
  "punish_id" : 8,
  "hit_id" : 1,
  "game_frame" : 3152,
  "anim_frame" : 15,
  "damage" : 1,
  "opening" : "EDGEGUARDING",
  "kill_dir" : "NEUT"
  },
  {
  "move_id" : 255,
  "move_name" : "(o)",
  "cancel_type" : 0,
  "cancel_name" : "",
  "punish_id" : 8,
  "hit_id" : 1,
  "game_frame" : 3212,
  "anim_frame" : 10,
  "damage" : 1,
  "opening" : "EDGEGUARDING",
  "kill_dir" : "NEUT"
  },
  {
  "move_id" : 17,
  "move_name" : "Dair",
  "cancel_type" : 0,
  "cancel_name" : "",
  "punish_id" : 9,
  "hit_id" : 1,
  "game_frame" : 3429,
  "anim_frame" : 16,
  "damage" : 1.88,
  "opening" : "POKING",
  "kill_dir" : "NEUT"
  },
  {
  "move_id" : 17,
  "move_name" : "Dair",
  "cancel_type" : 0,
  "cancel_name" : "",
  "punish_id" : 9,
  "hit_id" : 2,
  "game_frame" : 3434,
  "anim_frame" : 19,
  "damage" : 1.72,
  "opening" : "PUNISHING",
  "kill_dir" : "NEUT"
  },
  {
  "move_id" : 17,
  "move_name" : "Dair",
  "cancel_type" : 0,
  "cancel_name" : "",
  "punish_id" : 9,
  "hit_id" : 3,
  "game_frame" : 3440,
  "anim_frame" : 23,
  "damage" : 1.72,
  "opening" : "PUNISHING",
  "kill_dir" : "NEUT"
  },
  {
  "move_id" : 14,
  "move_name" : "Fair",
  "cancel_type" : 0,
  "cancel_name" : "",
  "punish_id" : 10,
  "hit_id" : 1,
  "game_frame" : 4017,
  "anim_frame" : 6,
  "damage" : 10,
  "opening" : "RECOVERING",
  "kill_dir" : "NEUT"
  },
  {
  "move_id" : 255,
  "move_name" : "(o)",
  "cancel_type" : 0,
  "cancel_name" : "",
  "punish_id" : 10,
  "hit_id" : 1,
  "game_frame" : 4104,
  "anim_frame" : 14,
  "damage" : 1,
  "opening" : "EDGEGUARDING",
  "kill_dir" : "NEUT"
  },
  {
  "move_id" : 255,
  "move_name" : "(o)",
  "cancel_type" : 0,
  "cancel_name" : "",
  "punish_id" : 10,
  "hit_id" : 1,
  "game_frame" : 4164,
  "anim_frame" : 2,
  "damage" : 1,
  "opening" : "EDGEGUARDING",
  "kill_dir" : "NEUT"
  },
  {
  "move_id" : 15,
  "move_name" : "Bair",
  "cancel_type" : 0,
  "cancel_name" : "",
  "punish_id" : 10,
  "hit_id" : 1,
  "game_frame" : 4219,
  "anim_frame" : 8,
  "damage" : 11.16,
  "opening" : "EDGEGUARDING",
  "kill_dir" : "LEFT"
  },
  {
  "move_id" : 13,
  "move_name" : "Nair",
  "cancel_type" : 2,
  "cancel_name" : "AC",
  "punish_id" : 11,
  "hit_id" : 1,
  "game_frame" : 4635,
  "anim_frame" : 23,
  "damage" : 9,
  "opening" : "POKING",
  "kill_dir" : "NEUT"
  },
  {
  "move_id" : 13,
  "move_name" : "Nair",
  "cancel_type" : 2,
  "cancel_name" : "AC",
  "punish_id" : 12,
  "hit_id" : 1,
  "game_frame" : 4952,
  "anim_frame" : 15,
  "damage" : 8.19,
  "opening" : "POKING",
  "kill_dir" : "NEUT"
  },
  {
  "move_id" : 13,
  "move_name" : "Nair",
  "cancel_type" : 2,
  "cancel_name" : "AC",
  "punish_id" : 13,
  "hit_id" : 1,
  "game_frame" : 5138,
  "anim_frame" : 16,
  "damage" : 7.47,
  "opening" : "POKING",
  "kill_dir" : "NEUT"
  },
  {
  "move_id" : 16,
  "move_name" : "Uair",
  "cancel_type" : 0,
  "cancel_name" : "",
  "punish_id" : 14,
  "hit_id" : 1,
  "game_frame" : 5242,
  "anim_frame" : 8,
  "damage" : 12,
  "opening" : "POKING",
  "kill_dir" : "NEUT"
  },
  {
  "move_id" : 13,
  "move_name" : "Nair",
  "cancel_type" : 0,
  "cancel_name" : "",
  "punish_id" : 15,
  "hit_id" : 1,
  "game_frame" : 5382,
  "anim_frame" : 5,
  "damage" : 9.48,
  "opening" : "POKING",
  "kill_dir" : "NEUT"
  },
  {
  "move_id" : 17,
  "move_name" : "Dair",
  "cancel_type" : 2,
  "cancel_name" : "AC",
  "punish_id" : 16,
  "hit_id" : 1,
  "game_frame" : 5564,
  "anim_frame" : 4,
  "damage" : 1.96,
  "opening" : "POKING",
  "kill_dir" : "NEUT"
  },
  {
  "move_id" : 17,
  "move_name" : "Dair",
  "cancel_type" : 2,
  "cancel_name" : "AC",
  "punish_id" : 16,
  "hit_id" : 2,
  "game_frame" : 5569,
  "anim_frame" : 7,
  "damage" : 1.8,
  "opening" : "PUNISHING",
  "kill_dir" : "NEUT"
  },
  {
  "move_id" : 17,
  "move_name" : "Dair",
  "cancel_type" : 2,
  "cancel_name" : "AC",
  "punish_id" : 16,
  "hit_id" : 3,
  "game_frame" : 5574,
  "anim_frame" : 10,
  "damage" : 1.8,
  "opening" : "PUNISHING",
  "kill_dir" : "NEUT"
  },
  {
  "move_id" : 17,
  "move_name" : "Dair",
  "cancel_type" : 2,
  "cancel_name" : "AC",
  "punish_id" : 16,
  "hit_id" : 4,
  "game_frame" : 5579,
  "anim_frame" : 13,
  "damage" : 1.8,
  "opening" : "PUNISHING",
  "kill_dir" : "NEUT"
  },
  {
  "move_id" : 53,
  "move_name" : "Fthrow",
  "cancel_type" : 0,
  "cancel_name" : "",
  "punish_id" : 17,
  "hit_id" : 1,
  "game_frame" : 5826,
  "anim_frame" : 9,
  "damage" : 12,
  "opening" : "TECHCHASING",
  "kill_dir" : "NEUT"
  },
  {
  "move_id" : 14,
  "move_name" : "Fair",
  "cancel_type" : 0,
  "cancel_name" : "",
  "punish_id" : 18,
  "hit_id" : 1,
  "game_frame" : 6068,
  "anim_frame" : 6,
  "damage" : 9.9,
  "opening" : "SHARKING",
  "kill_dir" : "NEUT"
  },
  {
  "move_id" : 15,
  "move_name" : "Bair",
  "cancel_type" : 2,
  "cancel_name" : "AC",
  "punish_id" : 19,
  "hit_id" : 1,
  "game_frame" : 6330,
  "anim_frame" : 9,
  "damage" : 11.88,
  "opening" : "POKING",
  "kill_dir" : "NEUT"
  },
  {
  "move_id" : 17,
  "move_name" : "Dair",
  "cancel_type" : 1,
  "cancel_name" : "LC",
  "punish_id" : 20,
  "hit_id" : 1,
  "game_frame" : 6694,
  "anim_frame" : 4,
  "damage" : 1.88,
  "opening" : "POKING",
  "kill_dir" : "NEUT"
  },
  {
  "move_id" : 17,
  "move_name" : "Dair",
  "cancel_type" : 1,
  "cancel_name" : "LC",
  "punish_id" : 20,
  "hit_id" : 2,
  "game_frame" : 6699,
  "anim_frame" : 7,
  "damage" : 1.72,
  "opening" : "PUNISHING",
  "kill_dir" : "NEUT"
  },
  {
  "move_id" : 17,
  "move_name" : "Dair",
  "cancel_type" : 1,
  "cancel_name" : "LC",
  "punish_id" : 20,
  "hit_id" : 3,
  "game_frame" : 6704,
  "anim_frame" : 10,
  "damage" : 1.72,
  "opening" : "PUNISHING",
  "kill_dir" : "NEUT"
  },
  {
  "move_id" : 17,
  "move_name" : "Dair",
  "cancel_type" : 1,
  "cancel_name" : "LC",
  "punish_id" : 20,
  "hit_id" : 4,
  "game_frame" : 6709,
  "anim_frame" : 13,
  "damage" : 1.72,
  "opening" : "PUNISHING",
  "kill_dir" : "NEUT"
  },
  {
  "move_id" : 17,
  "move_name" : "Dair",
  "cancel_type" : 1,
  "cancel_name" : "LC",
  "punish_id" : 20,
  "hit_id" : 5,
  "game_frame" : 6714,
  "anim_frame" : 16,
  "damage" : 1.72,
  "opening" : "PUNISHING",
  "kill_dir" : "NEUT"
  },
  {
  "move_id" : 17,
  "move_name" : "Dair",
  "cancel_type" : 1,
  "cancel_name" : "LC",
  "punish_id" : 20,
  "hit_id" : 6,
  "game_frame" : 6719,
  "anim_frame" : 19,
  "damage" : 1.72,
  "opening" : "PUNISHING",
  "kill_dir" : "NEUT"
  },
  {
  "move_id" : 17,
  "move_name" : "Dair",
  "cancel_type" : 1,
  "cancel_name" : "LC",
  "punish_id" : 20,
  "hit_id" : 7,
  "game_frame" : 6724,
  "anim_frame" : 22,
  "damage" : 1.72,
  "opening" : "PUNISHING",
  "kill_dir" : "NEUT"
  },
  {
  "move_id" : 17,
  "move_name" : "Dair",
  "cancel_type" : 1,
  "cancel_name" : "LC",
  "punish_id" : 21,
  "hit_id" : 1,
  "game_frame" : 6831,
  "anim_frame" : 10,
  "damage" : 1.72,
  "opening" : "POKING",
  "kill_dir" : "NEUT"
  },
  {
  "move_id" : 17,
  "move_name" : "Dair",
  "cancel_type" : 1,
  "cancel_name" : "LC",
  "punish_id" : 21,
  "hit_id" : 2,
  "game_frame" : 6836,
  "anim_frame" : 13,
  "damage" : 1.58,
  "opening" : "PUNISHING",
  "kill_dir" : "NEUT"
  },
  {
  "move_id" : 17,
  "move_name" : "Dair",
  "cancel_type" : 1,
  "cancel_name" : "LC",
  "punish_id" : 21,
  "hit_id" : 3,
  "game_frame" : 6841,
  "anim_frame" : 16,
  "damage" : 1.58,
  "opening" : "PUNISHING",
  "kill_dir" : "NEUT"
  },
  {
  "move_id" : 17,
  "move_name" : "Dair",
  "cancel_type" : 1,
  "cancel_name" : "LC",
  "punish_id" : 21,
  "hit_id" : 4,
  "game_frame" : 6846,
  "anim_frame" : 19,
  "damage" : 1.58,
  "opening" : "PUNISHING",
  "kill_dir" : "NEUT"
  },
  {
  "move_id" : 17,
  "move_name" : "Dair",
  "cancel_type" : 1,
  "cancel_name" : "LC",
  "punish_id" : 21,
  "hit_id" : 5,
  "game_frame" : 6851,
  "anim_frame" : 22,
  "damage" : 1.58,
  "opening" : "PUNISHING",
  "kill_dir" : "NEUT"
  },
  {
  "move_id" : 17,
  "move_name" : "Dair",
  "cancel_type" : 1,
  "cancel_name" : "LC",
  "punish_id" : 21,
  "hit_id" : 6,
  "game_frame" : 6856,
  "anim_frame" : 25,
  "damage" : 1.58,
  "opening" : "PUNISHING",
  "kill_dir" : "NEUT"
  },
  {
  "move_id" : 11,
  "move_name" : "Usmash",
  "cancel_type" : 0,
  "cancel_name" : "",
  "punish_id" : 21,
  "hit_id" : 1,
  "game_frame" : 6887,
  "anim_frame" : 8,
  "damage" : 14,
  "opening" : "PUNISHING",
  "kill_dir" : "UP"
  },
  {
  "move_id" : 13,
  "move_name" : "Nair",
  "cancel_type" : 0,
  "cancel_name" : "",
  "punish_id" : 22,
  "hit_id" : 1,
  "game_frame" : 7504,
  "anim_frame" : 8,
  "damage" : 8.82,
  "opening" : "POKING",
  "kill_dir" : "NEUT"
  },
  {
  "move_id" : 15,
  "move_name" : "Bair",
  "cancel_type" : 0,
  "cancel_name" : "",
  "punish_id" : 23,
  "hit_id" : 1,
  "game_frame" : 8488,
  "anim_frame" : 8,
  "damage" : 12,
  "opening" : "POKING",
  "kill_dir" : "NEUT"
  },
  {
  "move_id" : 15,
  "move_name" : "Bair",
  "cancel_type" : 2,
  "cancel_name" : "AC",
  "punish_id" : 24,
  "hit_id" : 1,
  "game_frame" : 8710,
  "anim_frame" : 9,
  "damage" : 10.92,
  "opening" : "POKING",
  "kill_dir" : "NEUT"
  },
  {
  "move_id" : 15,
  "move_name" : "Bair",
  "cancel_type" : 2,
  "cancel_name" : "AC",
  "punish_id" : 25,
  "hit_id" : 1,
  "game_frame" : 9317,
  "anim_frame" : 8,
  "damage" : 9.96,
  "opening" : "POKING",
  "kill_dir" : "NEUT"
  },
  {
  "move_id" : 11,
  "move_name" : "Usmash",
  "cancel_type" : 0,
  "cancel_name" : "",
  "punish_id" : 25,
  "hit_id" : 1,
  "game_frame" : 9354,
  "anim_frame" : 6,
  "damage" : 14,
  "opening" : "PUNISHING",
  "kill_dir" : "NEUT"
  },
  {
  "move_id" : 15,
  "move_name" : "Bair",
  "cancel_type" : 0,
  "cancel_name" : "",
  "punish_id" : 25,
  "hit_id" : 1,
  "game_frame" : 9455,
  "anim_frame" : 9,
  "damage" : 9.48,
  "opening" : "SHARKING",
  "kill_dir" : "NEUT"
  },
  {
  "move_id" : 14,
  "move_name" : "Fair",
  "cancel_type" : 0,
  "cancel_name" : "",
  "punish_id" : 26,
  "hit_id" : 1,
  "game_frame" : 9814,
  "anim_frame" : 6,
  "damage" : 12,
  "opening" : "RECOVERING",
  "kill_dir" : "NEUT"
  },
  {
  "move_id" : 13,
  "move_name" : "Nair",
  "cancel_type" : 2,
  "cancel_name" : "AC",
  "punish_id" : 27,
  "hit_id" : 1,
  "game_frame" : 10340,
  "anim_frame" : 7,
  "damage" : 9,
  "opening" : "POKING",
  "kill_dir" : "NEUT"
  },
  {
  "move_id" : 15,
  "move_name" : "Bair",
  "cancel_type" : 2,
  "cancel_name" : "AC",
  "punish_id" : 28,
  "hit_id" : 1,
  "game_frame" : 11123,
  "anim_frame" : 9,
  "damage" : 9.72,
  "opening" : "POKING",
  "kill_dir" : "NEUT"
  },
  {
  "move_id" : 255,
  "move_name" : "(o)",
  "cancel_type" : 0,
  "cancel_name" : "",
  "punish_id" : 28,
  "hit_id" : 1,
  "game_frame" : 11218,
  "anim_frame" : 0,
  "damage" : 1,
  "opening" : "EDGEGUARDING",
  "kill_dir" : "NEUT"
  },
  {
  "move_id" : 255,
  "move_name" : "(o)",
  "cancel_type" : 0,
  "cancel_name" : "",
  "punish_id" : 28,
  "hit_id" : 1,
  "game_frame" : 11278,
  "anim_frame" : 23,
  "damage" : 1,
  "opening" : "EDGEGUARDING",
  "kill_dir" : "NEUT"
  },
  {
  "move_id" : 14,
  "move_name" : "Fair",
  "cancel_type" : 0,
  "cancel_name" : "",
  "punish_id" : 29,
  "hit_id" : 1,
  "game_frame" : 12065,
  "anim_frame" : 9,
  "damage" : 7,
  "opening" : "POKING",
  "kill_dir" : "NEUT"
  },
  {
  "move_id" : 14,
  "move_name" : "Fair",
  "cancel_type" : 0,
  "cancel_name" : "",
  "punish_id" : 29,
  "hit_id" : 1,
  "game_frame" : 12105,
  "anim_frame" : 7,
  "damage" : 10.92,
  "opening" : "PUNISHING",
  "kill_dir" : "NEUT"
  },
  {
  "move_id" : 255,
  "move_name" : "(o)",
  "cancel_type" : 0,
  "cancel_name" : "",
  "punish_id" : 29,
  "hit_id" : 1,
  "game_frame" : 12190,
  "anim_frame" : 10,
  "damage" : 1,
  "opening" : "EDGEGUARDING",
  "kill_dir" : "NEUT"
  },
  {
  "move_id" : 15,
  "move_name" : "Bair",
  "cancel_type" : 2,
  "cancel_name" : "AC",
  "punish_id" : 29,
  "hit_id" : 1,
  "game_frame" : 12395,
  "anim_frame" : 9,
  "damage" : 12,
  "opening" : "EDGEGUARDING",
  "kill_dir" : "LEFT"
  },
  {
  "move_id" : 13,
  "move_name" : "Nair",
  "cancel_type" : 2,
  "cancel_name" : "AC",
  "punish_id" : 30,
  "hit_id" : 1,
  "game_frame" : 12920,
  "anim_frame" : 20,
  "damage" : 9,
  "opening" : "RECOVERING",
  "kill_dir" : "NEUT"
  },
  {
  "move_id" : 15,
  "move_name" : "Bair",
  "cancel_type" : 1,
  "cancel_name" : "LC",
  "punish_id" : 31,
  "hit_id" : 1,
  "game_frame" : 14364,
  "anim_frame" : 9,
  "damage" : 11.04,
  "opening" : "POKING",
  "kill_dir" : "NEUT"
  },
  {
  "move_id" : 15,
  "move_name" : "Bair",
  "cancel_type" : 1,
  "cancel_name" : "LC",
  "punish_id" : 31,
  "hit_id" : 1,
  "game_frame" : 14402,
  "anim_frame" : 9,
  "damage" : 10.08,
  "opening" : "PUNISHING",
  "kill_dir" : "NEUT"
  },
  {
  "move_id" : 15,
  "move_name" : "Bair",
  "cancel_type" : 0,
  "cancel_name" : "",
  "punish_id" : 31,
  "hit_id" : 1,
  "game_frame" : 14490,
  "anim_frame" : 8,
  "damage" : 10.08,
  "opening" : "PUNISHING",
  "kill_dir" : "NEUT"
  },
  {
  "move_id" : 15,
  "move_name" : "Bair",
  "cancel_type" : 0,
  "cancel_name" : "",
  "punish_id" : 31,
  "hit_id" : 1,
  "game_frame" : 14544,
  "anim_frame" : 9,
  "damage" : 9.24,
  "opening" : "PUNISHING",
  "kill_dir" : "NEUT"
  },
  {
  "move_id" : 14,
  "move_name" : "Fair",
  "cancel_type" : 0,
  "cancel_name" : "",
  "punish_id" : 32,
  "hit_id" : 1,
  "game_frame" : 14849,
  "anim_frame" : 8,
  "damage" : 6.51,
  "opening" : "POKING",
  "kill_dir" : "NEUT"
  },
  {
  "move_id" : 14,
  "move_name" : "Fair",
  "cancel_type" : 0,
  "cancel_name" : "",
  "punish_id" : 33,
  "hit_id" : 1,
  "game_frame" : 15817,
  "anim_frame" : 10,
  "damage" : 6.02,
  "opening" : "RECOVERING",
  "kill_dir" : "NEUT"
  },
  {
  "move_id" : 53,
  "move_name" : "Fthrow",
  "cancel_type" : 0,
  "cancel_name" : "",
  "punish_id" : 34,
  "hit_id" : 1,
  "game_frame" : 16102,
  "anim_frame" : 9,
  "damage" : 12,
  "opening" : "TECHCHASING",
  "kill_dir" : "NEUT"
  }
 ],
 "punishes" : [
  {
  "start_frame" : 361,
  "end_frame" : 412,
  "start_pct" : 0,
  "end_pct" : 9,
  "num_moves" : 1,
  "last_move_id" : 13,
  "last_move_name" : "Nair",
  "opening" : "UNUSED",
  "kill_dir" : "NEUT"
  },
  {
  "start_frame" : 560,
  "end_frame" : 607,
  "start_pct" : 9,
  "end_pct" : 17.19,
  "num_moves" : 1,
  "last_move_id" : 13,
  "last_move_name" : "Nair",
  "opening" : "UNUSED",
  "kill_dir" : "NEUT"
  },
  {
  "start_frame" : 797,
  "end_frame" : 844,
  "start_pct" : 17.19,
  "end_pct" : 24.66,
  "num_moves" : 1,
  "last_move_id" : 13,
  "last_move_name" : "Nair",
  "opening" : "UNUSED",
  "kill_dir" : "NEUT"
  },
  {
  "start_frame" : 1382,
  "end_frame" : 1513,
  "start_pct" : 24.66,
  "end_pct" : 47.58,
  "num_moves" : 2,
  "last_move_id" : 15,
  "last_move_name" : "Bair",
  "opening" : "UNUSED",
  "kill_dir" : "NEUT"
  },
  {
  "start_frame" : 1758,
  "end_frame" : 1879,
  "start_pct" : 47.58,
  "end_pct" : 59.58,
  "num_moves" : 1,
  "last_move_id" : 53,
  "last_move_name" : "Fthrow",
  "opening" : "UNUSED",
  "kill_dir" : "NEUT"
  },
  {
  "start_frame" : 1907,
  "end_frame" : 1969,
  "start_pct" : 59.58,
  "end_pct" : 67.23,
  "num_moves" : 1,
  "last_move_id" : 13,
  "last_move_name" : "Nair",
  "opening" : "UNUSED",
  "kill_dir" : "NEUT"
  },
  {
  "start_frame" : 2477,
  "end_frame" : 2686,
  "start_pct" : 67.23,
  "end_pct" : 83.05,
  "num_moves" : 3,
  "last_move_id" : 53,
  "last_move_name" : "Fthrow",
  "opening" : "UNUSED",
  "kill_dir" : "NEUT"
  },
  {
  "start_frame" : 2929,
  "end_frame" : 3066,
  "start_pct" : 83.05,
  "end_pct" : 93.97,
  "num_moves" : 1,
  "last_move_id" : 53,
  "last_move_name" : "Fthrow",
  "opening" : "UNUSED",
  "kill_dir" : "NEUT"
  },
  {
  "start_frame" : 3074,
  "end_frame" : 3386,
  "start_pct" : 93.97,
  "end_pct" : 107.97,
  "num_moves" : 3,
  "last_move_id" : 15,
  "last_move_name" : "Bair",
  "opening" : "UNUSED",
  "kill_dir" : "NEUT"
  },
  {
  "start_frame" : 3429,
  "end_frame" : 3542,
  "start_pct" : 107.97,
  "end_pct" : 113.29,
  "num_moves" : 3,
  "last_move_id" : 17,
  "last_move_name" : "Dair",
  "opening" : "UNUSED",
  "kill_dir" : "NEUT"
  },
  {
  "start_frame" : 4017,
  "end_frame" : 4294,
  "start_pct" : 113.29,
  "end_pct" : 136.45,
  "num_moves" : 4,
  "last_move_id" : 15,
  "last_move_name" : "Bair",
  "opening" : "UNUSED",
  "kill_dir" : "LEFT"
  },
  {
  "start_frame" : 4635,
  "end_frame" : 4680,
  "start_pct" : 0,
  "end_pct" : 9,
  "num_moves" : 1,
  "last_move_id" : 13,
  "last_move_name" : "Nair",
  "opening" : "UNUSED",
  "kill_dir" : "NEUT"
  },
  {
  "start_frame" : 4952,
  "end_frame" : 5015,
  "start_pct" : 9,
  "end_pct" : 17.19,
  "num_moves" : 1,
  "last_move_id" : 13,
  "last_move_name" : "Nair",
  "opening" : "UNUSED",
  "kill_dir" : "NEUT"
  },
  {
  "start_frame" : 5138,
  "end_frame" : 5192,
  "start_pct" : 17.19,
  "end_pct" : 24.66,
  "num_moves" : 1,
  "last_move_id" : 13,
  "last_move_name" : "Nair",
  "opening" : "UNUSED",
  "kill_dir" : "NEUT"
  },
  {
  "start_frame" : 5242,
  "end_frame" : 5378,
  "start_pct" : 24.66,
  "end_pct" : 36.66,
  "num_moves" : 1,
  "last_move_id" : 16,
  "last_move_name" : "Uair",
  "opening" : "UNUSED",
  "kill_dir" : "NEUT"
  },
  {
  "start_frame" : 5382,
  "end_frame" : 5439,
  "start_pct" : 36.66,
  "end_pct" : 46.14,
  "num_moves" : 1,
  "last_move_id" : 13,
  "last_move_name" : "Nair",
  "opening" : "UNUSED",
  "kill_dir" : "NEUT"
  },
  {
  "start_frame" : 5564,
  "end_frame" : 5631,
  "start_pct" : 46.14,
  "end_pct" : 53.5,
  "num_moves" : 4,
  "last_move_id" : 17,
  "last_move_name" : "Dair",
  "opening" : "UNUSED",
  "kill_dir" : "NEUT"
  },
  {
  "start_frame" : 5826,
  "end_frame" : 6009,
  "start_pct" : 53.5,
  "end_pct" : 65.5,
  "num_moves" : 1,
  "last_move_id" : 53,
  "last_move_name" : "Fthrow",
  "opening" : "UNUSED",
  "kill_dir" : "NEUT"
  },
  {
  "start_frame" : 6068,
  "end_frame" : 6234,
  "start_pct" : 65.5,
  "end_pct" : 75.4,
  "num_moves" : 1,
  "last_move_id" : 14,
  "last_move_name" : "Fair",
  "opening" : "UNUSED",
  "kill_dir" : "NEUT"
  },
  {
  "start_frame" : 6330,
  "end_frame" : 6464,
  "start_pct" : 75.4,
  "end_pct" : 87.28,
  "num_moves" : 1,
  "last_move_id" : 15,
  "last_move_name" : "Bair",
  "opening" : "UNUSED",
  "kill_dir" : "NEUT"
  },
  {
  "start_frame" : 6694,
  "end_frame" : 6809,
  "start_pct" : 87.28,
  "end_pct" : 99.48,
  "num_moves" : 7,
  "last_move_id" : 17,
  "last_move_name" : "Dair",
  "opening" : "UNUSED",
  "kill_dir" : "NEUT"
  },
  {
  "start_frame" : 6831,
  "end_frame" : 6965,
  "start_pct" : 99.48,
  "end_pct" : 123.1,
  "num_moves" : 7,
  "last_move_id" : 11,
  "last_move_name" : "Usmash",
  "opening" : "UNUSED",
  "kill_dir" : "UP"
  },
  {
  "start_frame" : 7504,
  "end_frame" : 7548,
  "start_pct" : 0,
  "end_pct" : 8.82,
  "num_moves" : 1,
  "last_move_id" : 13,
  "last_move_name" : "Nair",
  "opening" : "UNUSED",
  "kill_dir" : "NEUT"
  },
  {
  "start_frame" : 8488,
  "end_frame" : 8543,
  "start_pct" : 8.82,
  "end_pct" : 20.82,
  "num_moves" : 1,
  "last_move_id" : 15,
  "last_move_name" : "Bair",
  "opening" : "UNUSED",
  "kill_dir" : "NEUT"
  },
  {
  "start_frame" : 8710,
  "end_frame" : 8769,
  "start_pct" : 20.82,
  "end_pct" : 31.74,
  "num_moves" : 1,
  "last_move_id" : 15,
  "last_move_name" : "Bair",
  "opening" : "UNUSED",
  "kill_dir" : "NEUT"
  },
  {
  "start_frame" : 9317,
  "end_frame" : 9659,
  "start_pct" : 31.74,
  "end_pct" : 65.18,
  "num_moves" : 3,
  "last_move_id" : 15,
  "last_move_name" : "Bair",
  "opening" : "UNUSED",
  "kill_dir" : "NEUT"
  },
  {
  "start_frame" : 9814,
  "end_frame" : 9975,
  "start_pct" : 65.18,
  "end_pct" : 77.18,
  "num_moves" : 1,
  "last_move_id" : 14,
  "last_move_name" : "Fair",
  "opening" : "UNUSED",
  "kill_dir" : "NEUT"
  },
  {
  "start_frame" : 10340,
  "end_frame" : 10459,
  "start_pct" : 77.18,
  "end_pct" : 86.18,
  "num_moves" : 1,
  "last_move_id" : 13,
  "last_move_name" : "Nair",
  "opening" : "UNUSED",
  "kill_dir" : "NEUT"
  },
  {
  "start_frame" : 11123,
  "end_frame" : 11433,
  "start_pct" : 86.18,
  "end_pct" : 97.9,
  "num_moves" : 3,
  "last_move_id" : 15,
  "last_move_name" : "Bair",
  "opening" : "UNUSED",
  "kill_dir" : "NEUT"
  },
  {
  "start_frame" : 12065,
  "end_frame" : 12478,
  "start_pct" : 97.9,
  "end_pct" : 128.82,
  "num_moves" : 4,
  "last_move_id" : 15,
  "last_move_name" : "Bair",
  "opening" : "UNUSED",
  "kill_dir" : "LEFT"
  },
  {
  "start_frame" : 12920,
  "end_frame" : 12979,
  "start_pct" : 0,
  "end_pct" : 9,
  "num_moves" : 1,
  "last_move_id" : 13,
  "last_move_name" : "Nair",
  "opening" : "UNUSED",
  "kill_dir" : "NEUT"
  },
  {
  "start_frame" : 14364,
  "end_frame" : 14654,
  "start_pct" : 9,
  "end_pct" : 49.44,
  "num_moves" : 4,
  "last_move_id" : 15,
  "last_move_name" : "Bair",
  "opening" : "UNUSED",
  "kill_dir" : "NEUT"
  },
  {
  "start_frame" : 14849,
  "end_frame" : 14933,
  "start_pct" : 49.44,
  "end_pct" : 55.95,
  "num_moves" : 1,
  "last_move_id" : 14,
  "last_move_name" : "Fair",
  "opening" : "UNUSED",
  "kill_dir" : "NEUT"
  },
  {
  "start_frame" : 15817,
  "end_frame" : 15874,
  "start_pct" : 55.95,
  "end_pct" : 61.97,
  "num_moves" : 1,
  "last_move_id" : 14,
  "last_move_name" : "Fair",
  "opening" : "UNUSED",
  "kill_dir" : "NEUT"
  },
  {
  "start_frame" : 16102,
  "end_frame" : 16233,
  "start_pct" : 61.97,
  "end_pct" : 73.97,
  "num_moves" : 1,
  "last_move_id" : 53,
  "last_move_name" : "Fthrow",
  "opening" : "UNUSED",
  "kill_dir" : "NEUT"
  }
 ]
 }
]
}

